<?xml version="1.0"?>
<sparql xmlns="http://www.w3.org/2005/sparql-results#">
  <head>
    <variable name="refArea"/>
    <variable name="obsValue"/>
  </head>
  <results>
    <result>
      <binding name="refArea">
        <uri>http://worldbank.270a.info/classification/country/AW</uri>
      </binding>
      <binding name="obsValue">
        <literal datatype="http://www.w3.org/2001/XMLSchema#decimal">672</literal>
      </binding>
    </result>
    <result>
      <binding name="refArea">
        <uri>http://worldbank.270a.info/classification/country/AF</uri>
      </binding>
      <binding name="obsValue">
        <literal datatype="http://www.w3.org/2001/XMLSchema#decimal">536701</literal>
      </binding>
    </result>
    <result>
      <binding name="refArea">
        <uri>http://worldbank.270a.info/classification/country/AO</uri>
      </binding>
      <binding name="obsValue">
        <literal datatype="http://www.w3.org/2001/XMLSchema#decimal">335055</literal>
      </binding>
    </result>
    <result>
      <binding name="refArea">
        <uri>http://worldbank.270a.info/classification/country/AL</uri>
      </binding>
      <binding name="obsValue">
        <literal datatype="http://www.w3.org/2001/XMLSchema#decimal">24312</literal>
      </binding>
    </result>
    <result>
      <binding name="refArea">
        <uri>http://worldbank.270a.info/classification/country/AE</uri>
      </binding>
      <binding name="obsValue">
        <literal datatype="http://www.w3.org/2001/XMLSchema#decimal">35845</literal>
      </binding>
    </result>
    <result>
      <binding name="refArea">
        <uri>http://worldbank.270a.info/classification/country/AR</uri>
      </binding>
      <binding name="obsValue">
        <literal datatype="http://www.w3.org/2001/XMLSchema#decimal">336948</literal>
      </binding>
    </result>
    <result>
      <binding name="refArea">
        <uri>http://worldbank.270a.info/classification/country/AM</uri>
      </binding>
      <binding name="obsValue">
        <literal datatype="http://www.w3.org/2001/XMLSchema#decimal">16706</literal>
      </binding>
    </result>
    <result>
      <binding name="refArea">
        <uri>http://worldbank.270a.info/classification/country/AU</uri>
      </binding>
      <binding name="obsValue">
        <literal datatype="http://www.w3.org/2001/XMLSchema#decimal">128359</literal>
      </binding>
    </result>
    <result>
      <binding name="refArea">
        <uri>http://worldbank.270a.info/classification/country/AT</uri>
      </binding>
      <binding name="obsValue">
        <literal datatype="http://www.w3.org/2001/XMLSchema#decimal">38348</literal>
      </binding>
    </result>
    <result>
      <binding name="refArea">
        <uri>http://worldbank.270a.info/classification/country/AZ</uri>
      </binding>
      <binding name="obsValue">
        <literal datatype="http://www.w3.org/2001/XMLSchema#decimal">58989</literal>
      </binding>
    </result>
    <result>
      <binding name="refArea">
        <uri>http://worldbank.270a.info/classification/country/BI</uri>
      </binding>
      <binding name="obsValue">
        <literal datatype="http://www.w3.org/2001/XMLSchema#decimal">181398</literal>
      </binding>
    </result>
    <result>
      <binding name="refArea">
        <uri>http://worldbank.270a.info/classification/country/BE</uri>
      </binding>
      <binding name="obsValue">
        <literal datatype="http://www.w3.org/2001/XMLSchema#decimal">53967</literal>
      </binding>
    </result>
    <result>
      <binding name="refArea">
        <uri>http://worldbank.270a.info/classification/country/BJ</uri>
      </binding>
      <binding name="obsValue">
        <literal datatype="http://www.w3.org/2001/XMLSchema#decimal">160539</literal>
      </binding>
    </result>
    <result>
      <binding name="refArea">
        <uri>http://worldbank.270a.info/classification/country/BF</uri>
      </binding>
      <binding name="obsValue">
        <literal datatype="http://www.w3.org/2001/XMLSchema#decimal">277091</literal>
      </binding>
    </result>
    <result>
      <binding name="refArea">
        <uri>http://worldbank.270a.info/classification/country/BD</uri>
      </binding>
      <binding name="obsValue">
        <literal datatype="http://www.w3.org/2001/XMLSchema#decimal">1832905</literal>
      </binding>
    </result>
    <result>
      <binding name="refArea">
        <uri>http://worldbank.270a.info/classification/country/BG</uri>
      </binding>
      <binding name="obsValue">
        <literal datatype="http://www.w3.org/2001/XMLSchema#decimal">32573</literal>
      </binding>
    </result>
    <result>
      <binding name="refArea">
        <uri>http://worldbank.270a.info/classification/country/BH</uri>
      </binding>
      <binding name="obsValue">
        <literal datatype="http://www.w3.org/2001/XMLSchema#decimal">6201</literal>
      </binding>
    </result>
    <result>
      <binding name="refArea">
        <uri>http://worldbank.270a.info/classification/country/BS</uri>
      </binding>
      <binding name="obsValue">
        <literal datatype="http://www.w3.org/2001/XMLSchema#decimal">2689</literal>
      </binding>
    </result>
    <result>
      <binding name="refArea">
        <uri>http://worldbank.270a.info/classification/country/BA</uri>
      </binding>
      <binding name="obsValue">
        <literal datatype="http://www.w3.org/2001/XMLSchema#decimal">15761</literal>
      </binding>
    </result>
    <result>
      <binding name="refArea">
        <uri>http://worldbank.270a.info/classification/country/BY</uri>
      </binding>
      <binding name="obsValue">
        <literal datatype="http://www.w3.org/2001/XMLSchema#decimal">43894</literal>
      </binding>
    </result>
    <result>
      <binding name="refArea">
        <uri>http://worldbank.270a.info/classification/country/BZ</uri>
      </binding>
      <binding name="obsValue">
        <literal datatype="http://www.w3.org/2001/XMLSchema#decimal">3531</literal>
      </binding>
    </result>
    <result>
      <binding name="refArea">
        <uri>http://worldbank.270a.info/classification/country/BO</uri>
      </binding>
      <binding name="obsValue">
        <literal datatype="http://www.w3.org/2001/XMLSchema#decimal">121142</literal>
      </binding>
    </result>
    <result>
      <binding name="refArea">
        <uri>http://worldbank.270a.info/classification/country/BR</uri>
      </binding>
      <binding name="obsValue">
        <literal datatype="http://www.w3.org/2001/XMLSchema#decimal">1755190</literal>
      </binding>
    </result>
    <result>
      <binding name="refArea">
        <uri>http://worldbank.270a.info/classification/country/BB</uri>
      </binding>
      <binding name="obsValue">
        <literal datatype="http://www.w3.org/2001/XMLSchema#decimal">1562</literal>
      </binding>
    </result>
    <result>
      <binding name="refArea">
        <uri>http://worldbank.270a.info/classification/country/BN</uri>
      </binding>
      <binding name="obsValue">
        <literal datatype="http://www.w3.org/2001/XMLSchema#decimal">3939</literal>
      </binding>
    </result>
    <result>
      <binding name="refArea">
        <uri>http://worldbank.270a.info/classification/country/BT</uri>
      </binding>
      <binding name="obsValue">
        <literal datatype="http://www.w3.org/2001/XMLSchema#decimal">5685</literal>
      </binding>
    </result>
    <result>
      <binding name="refArea">
        <uri>http://worldbank.270a.info/classification/country/BW</uri>
      </binding>
      <binding name="obsValue">
        <literal datatype="http://www.w3.org/2001/XMLSchema#decimal">22089</literal>
      </binding>
    </result>
    <result>
      <binding name="refArea">
        <uri>http://worldbank.270a.info/classification/country/CF</uri>
      </binding>
      <binding name="obsValue">
        <literal datatype="http://www.w3.org/2001/XMLSchema#decimal">68476</literal>
      </binding>
    </result>
    <result>
      <binding name="refArea">
        <uri>http://worldbank.270a.info/classification/country/CA</uri>
      </binding>
      <binding name="obsValue">
        <literal datatype="http://www.w3.org/2001/XMLSchema#decimal">174762</literal>
      </binding>
    </result>
    <result>
      <binding name="refArea">
        <uri>http://worldbank.270a.info/classification/country/CH</uri>
      </binding>
      <binding name="obsValue">
        <literal datatype="http://www.w3.org/2001/XMLSchema#decimal">34342</literal>
      </binding>
    </result>
    <result>
      <binding name="refArea">
        <uri>http://worldbank.270a.info/classification/country/CL</uri>
      </binding>
      <binding name="obsValue">
        <literal datatype="http://www.w3.org/2001/XMLSchema#decimal">122675</literal>
      </binding>
    </result>
    <result>
      <binding name="refArea">
        <uri>http://worldbank.270a.info/classification/country/CN</uri>
      </binding>
      <binding name="obsValue">
        <literal datatype="http://www.w3.org/2001/XMLSchema#decimal">7777941</literal>
      </binding>
    </result>
    <result>
      <binding name="refArea">
        <uri>http://worldbank.270a.info/classification/country/CI</uri>
      </binding>
      <binding name="obsValue">
        <literal datatype="http://www.w3.org/2001/XMLSchema#decimal">287949</literal>
      </binding>
    </result>
    <result>
      <binding name="refArea">
        <uri>http://worldbank.270a.info/classification/country/CM</uri>
      </binding>
      <binding name="obsValue">
        <literal datatype="http://www.w3.org/2001/XMLSchema#decimal">282154</literal>
      </binding>
    </result>
    <result>
      <binding name="refArea">
        <uri>http://worldbank.270a.info/classification/country/CG</uri>
      </binding>
      <binding name="obsValue">
        <literal datatype="http://www.w3.org/2001/XMLSchema#decimal">61009</literal>
      </binding>
    </result>
    <result>
      <binding name="refArea">
        <uri>http://worldbank.270a.info/classification/country/CO</uri>
      </binding>
      <binding name="obsValue">
        <literal datatype="http://www.w3.org/2001/XMLSchema#decimal">412943</literal>
      </binding>
    </result>
    <result>
      <binding name="refArea">
        <uri>http://worldbank.270a.info/classification/country/KM</uri>
      </binding>
      <binding name="obsValue">
        <literal datatype="http://www.w3.org/2001/XMLSchema#decimal">13092</literal>
      </binding>
    </result>
    <result>
      <binding name="refArea">
        <uri>http://worldbank.270a.info/classification/country/CV</uri>
      </binding>
      <binding name="obsValue">
        <literal datatype="http://www.w3.org/2001/XMLSchema#decimal">7623</literal>
      </binding>
    </result>
    <result>
      <binding name="refArea">
        <uri>http://worldbank.270a.info/classification/country/CR</uri>
      </binding>
      <binding name="obsValue">
        <literal datatype="http://www.w3.org/2001/XMLSchema#decimal">38691</literal>
      </binding>
    </result>
    <result>
      <binding name="refArea">
        <uri>http://worldbank.270a.info/classification/country/CU</uri>
      </binding>
      <binding name="obsValue">
        <literal datatype="http://www.w3.org/2001/XMLSchema#decimal">55060</literal>
      </binding>
    </result>
    <result>
      <binding name="refArea">
        <uri>http://worldbank.270a.info/classification/country/CY</uri>
      </binding>
      <binding name="obsValue">
        <literal datatype="http://www.w3.org/2001/XMLSchema#decimal">5229</literal>
      </binding>
    </result>
    <result>
      <binding name="refArea">
        <uri>http://worldbank.270a.info/classification/country/CZ</uri>
      </binding>
      <binding name="obsValue">
        <literal datatype="http://www.w3.org/2001/XMLSchema#decimal">47049</literal>
      </binding>
    </result>
    <result>
      <binding name="refArea">
        <uri>http://worldbank.270a.info/classification/country/DE</uri>
      </binding>
      <binding name="obsValue">
        <literal datatype="http://www.w3.org/2001/XMLSchema#decimal">329408</literal>
      </binding>
    </result>
    <result>
      <binding name="refArea">
        <uri>http://worldbank.270a.info/classification/country/DJ</uri>
      </binding>
      <binding name="obsValue">
        <literal datatype="http://www.w3.org/2001/XMLSchema#decimal">10626</literal>
      </binding>
    </result>
    <result>
      <binding name="refArea">
        <uri>http://worldbank.270a.info/classification/country/DK</uri>
      </binding>
      <binding name="obsValue">
        <literal datatype="http://www.w3.org/2001/XMLSchema#decimal">29614</literal>
      </binding>
    </result>
    <result>
      <binding name="refArea">
        <uri>http://worldbank.270a.info/classification/country/DO</uri>
      </binding>
      <binding name="obsValue">
        <literal datatype="http://www.w3.org/2001/XMLSchema#decimal">109465</literal>
      </binding>
    </result>
    <result>
      <binding name="refArea">
        <uri>http://worldbank.270a.info/classification/country/DZ</uri>
      </binding>
      <binding name="obsValue">
        <literal datatype="http://www.w3.org/2001/XMLSchema#decimal">343643</literal>
      </binding>
    </result>
    <result>
      <binding name="refArea">
        <uri>http://worldbank.270a.info/classification/country/EC</uri>
      </binding>
      <binding name="obsValue">
        <literal datatype="http://www.w3.org/2001/XMLSchema#decimal">132454</literal>
      </binding>
    </result>
    <result>
      <binding name="refArea">
        <uri>http://worldbank.270a.info/classification/country/EG</uri>
      </binding>
      <binding name="obsValue">
        <literal datatype="http://www.w3.org/2001/XMLSchema#decimal">879580</literal>
      </binding>
    </result>
    <result>
      <binding name="refArea">
        <uri>http://worldbank.270a.info/classification/country/ER</uri>
      </binding>
      <binding name="obsValue">
        <literal datatype="http://www.w3.org/2001/XMLSchema#decimal">91603</literal>
      </binding>
    </result>
    <result>
      <binding name="refArea">
        <uri>http://worldbank.270a.info/classification/country/ES</uri>
      </binding>
      <binding name="obsValue">
        <literal datatype="http://www.w3.org/2001/XMLSchema#decimal">238832</literal>
      </binding>
    </result>
    <result>
      <binding name="refArea">
        <uri>http://worldbank.270a.info/classification/country/EE</uri>
      </binding>
      <binding name="obsValue">
        <literal datatype="http://www.w3.org/2001/XMLSchema#decimal">7080</literal>
      </binding>
    </result>
    <result>
      <binding name="refArea">
        <uri>http://worldbank.270a.info/classification/country/ET</uri>
      </binding>
      <binding name="obsValue">
        <literal datatype="http://www.w3.org/2001/XMLSchema#decimal">1407773</literal>
      </binding>
    </result>
    <result>
      <binding name="refArea">
        <uri>http://worldbank.270a.info/classification/country/FI</uri>
      </binding>
      <binding name="obsValue">
        <literal datatype="http://www.w3.org/2001/XMLSchema#decimal">29038</literal>
      </binding>
    </result>
    <result>
      <binding name="refArea">
        <uri>http://worldbank.270a.info/classification/country/FJ</uri>
      </binding>
      <binding name="obsValue">
        <literal datatype="http://www.w3.org/2001/XMLSchema#decimal">8062</literal>
      </binding>
    </result>
    <result>
      <binding name="refArea">
        <uri>http://worldbank.270a.info/classification/country/FR</uri>
      </binding>
      <binding name="obsValue">
        <literal datatype="http://www.w3.org/2001/XMLSchema#decimal">367480</literal>
      </binding>
    </result>
    <result>
      <binding name="refArea">
        <uri>http://worldbank.270a.info/classification/country/FM</uri>
      </binding>
      <binding name="obsValue">
        <literal datatype="http://www.w3.org/2001/XMLSchema#decimal">1281</literal>
      </binding>
    </result>
    <result>
      <binding name="refArea">
        <uri>http://worldbank.270a.info/classification/country/GA</uri>
      </binding>
      <binding name="obsValue">
        <literal datatype="http://www.w3.org/2001/XMLSchema#decimal">15856</literal>
      </binding>
    </result>
    <result>
      <binding name="refArea">
        <uri>http://worldbank.270a.info/classification/country/GB</uri>
      </binding>
      <binding name="obsValue">
        <literal datatype="http://www.w3.org/2001/XMLSchema#decimal">355233</literal>
      </binding>
    </result>
    <result>
      <binding name="refArea">
        <uri>http://worldbank.270a.info/classification/country/GE</uri>
      </binding>
      <binding name="obsValue">
        <literal datatype="http://www.w3.org/2001/XMLSchema#decimal">21151</literal>
      </binding>
    </result>
    <result>
      <binding name="refArea">
        <uri>http://worldbank.270a.info/classification/country/GH</uri>
      </binding>
      <binding name="obsValue">
        <literal datatype="http://www.w3.org/2001/XMLSchema#decimal">317936</literal>
      </binding>
    </result>
    <result>
      <binding name="refArea">
        <uri>http://worldbank.270a.info/classification/country/GN</uri>
      </binding>
      <binding name="obsValue">
        <literal datatype="http://www.w3.org/2001/XMLSchema#decimal">160048</literal>
      </binding>
    </result>
    <result>
      <binding name="refArea">
        <uri>http://worldbank.270a.info/classification/country/GM</uri>
      </binding>
      <binding name="obsValue">
        <literal datatype="http://www.w3.org/2001/XMLSchema#decimal">26794</literal>
      </binding>
    </result>
    <result>
      <binding name="refArea">
        <uri>http://worldbank.270a.info/classification/country/GW</uri>
      </binding>
      <binding name="obsValue">
        <literal datatype="http://www.w3.org/2001/XMLSchema#decimal">36049</literal>
      </binding>
    </result>
    <result>
      <binding name="refArea">
        <uri>http://worldbank.270a.info/classification/country/GQ</uri>
      </binding>
      <binding name="obsValue">
        <literal datatype="http://www.w3.org/2001/XMLSchema#decimal">8647</literal>
      </binding>
    </result>
    <result>
      <binding name="refArea">
        <uri>http://worldbank.270a.info/classification/country/GR</uri>
      </binding>
      <binding name="obsValue">
        <literal datatype="http://www.w3.org/2001/XMLSchema#decimal">50466</literal>
      </binding>
    </result>
    <result>
      <binding name="refArea">
        <uri>http://worldbank.270a.info/classification/country/GD</uri>
      </binding>
      <binding name="obsValue">
        <literal datatype="http://www.w3.org/2001/XMLSchema#decimal">848</literal>
      </binding>
    </result>
    <result>
      <binding name="refArea">
        <uri>http://worldbank.270a.info/classification/country/GT</uri>
      </binding>
      <binding name="obsValue">
        <literal datatype="http://www.w3.org/2001/XMLSchema#decimal">214320</literal>
      </binding>
    </result>
    <result>
      <binding name="refArea">
        <uri>http://worldbank.270a.info/classification/country/GY</uri>
      </binding>
      <binding name="obsValue">
        <literal datatype="http://www.w3.org/2001/XMLSchema#decimal">5471</literal>
      </binding>
    </result>
    <result>
      <binding name="refArea">
        <uri>http://worldbank.270a.info/classification/country/HK</uri>
      </binding>
      <binding name="obsValue">
        <literal datatype="http://www.w3.org/2001/XMLSchema#decimal">29820</literal>
      </binding>
    </result>
    <result>
      <binding name="refArea">
        <uri>http://worldbank.270a.info/classification/country/HN</uri>
      </binding>
      <binding name="obsValue">
        <literal datatype="http://www.w3.org/2001/XMLSchema#decimal">93952</literal>
      </binding>
    </result>
    <result>
      <binding name="refArea">
        <uri>http://worldbank.270a.info/classification/country/HR</uri>
      </binding>
      <binding name="obsValue">
        <literal datatype="http://www.w3.org/2001/XMLSchema#decimal">19624</literal>
      </binding>
    </result>
    <result>
      <binding name="refArea">
        <uri>http://worldbank.270a.info/classification/country/HT</uri>
      </binding>
      <binding name="obsValue">
        <literal datatype="http://www.w3.org/2001/XMLSchema#decimal">123559</literal>
      </binding>
    </result>
    <result>
      <binding name="refArea">
        <uri>http://worldbank.270a.info/classification/country/HU</uri>
      </binding>
      <binding name="obsValue">
        <literal datatype="http://www.w3.org/2001/XMLSchema#decimal">45001</literal>
      </binding>
    </result>
    <result>
      <binding name="refArea">
        <uri>http://worldbank.270a.info/classification/country/ID</uri>
      </binding>
      <binding name="obsValue">
        <literal datatype="http://www.w3.org/2001/XMLSchema#decimal">2062524</literal>
      </binding>
    </result>
    <result>
      <binding name="refArea">
        <uri>http://worldbank.270a.info/classification/country/IN</uri>
      </binding>
      <binding name="obsValue">
        <literal datatype="http://www.w3.org/2001/XMLSchema#decimal">11996230</literal>
      </binding>
    </result>
    <result>
      <binding name="refArea">
        <uri>http://worldbank.270a.info/classification/country/IE</uri>
      </binding>
      <binding name="obsValue">
        <literal datatype="http://www.w3.org/2001/XMLSchema#decimal">33894</literal>
      </binding>
    </result>
    <result>
      <binding name="refArea">
        <uri>http://worldbank.270a.info/classification/country/IR</uri>
      </binding>
      <binding name="obsValue">
        <literal datatype="http://www.w3.org/2001/XMLSchema#decimal">711781</literal>
      </binding>
    </result>
    <result>
      <binding name="refArea">
        <uri>http://worldbank.270a.info/classification/country/IQ</uri>
      </binding>
      <binding name="obsValue">
        <literal datatype="http://www.w3.org/2001/XMLSchema#decimal">415301</literal>
      </binding>
    </result>
    <result>
      <binding name="refArea">
        <uri>http://worldbank.270a.info/classification/country/IS</uri>
      </binding>
      <binding name="obsValue">
        <literal datatype="http://www.w3.org/2001/XMLSchema#decimal">2098</literal>
      </binding>
    </result>
    <result>
      <binding name="refArea">
        <uri>http://worldbank.270a.info/classification/country/IL</uri>
      </binding>
      <binding name="obsValue">
        <literal datatype="http://www.w3.org/2001/XMLSchema#decimal">66837</literal>
      </binding>
    </result>
    <result>
      <binding name="refArea">
        <uri>http://worldbank.270a.info/classification/country/IT</uri>
      </binding>
      <binding name="obsValue">
        <literal datatype="http://www.w3.org/2001/XMLSchema#decimal">263513</literal>
      </binding>
    </result>
    <result>
      <binding name="refArea">
        <uri>http://worldbank.270a.info/classification/country/JM</uri>
      </binding>
      <binding name="obsValue">
        <literal datatype="http://www.w3.org/2001/XMLSchema#decimal">25307</literal>
      </binding>
    </result>
    <result>
      <binding name="refArea">
        <uri>http://worldbank.270a.info/classification/country/JO</uri>
      </binding>
      <binding name="obsValue">
        <literal datatype="http://www.w3.org/2001/XMLSchema#decimal">74205</literal>
      </binding>
    </result>
    <result>
      <binding name="refArea">
        <uri>http://worldbank.270a.info/classification/country/JP</uri>
      </binding>
      <binding name="obsValue">
        <literal datatype="http://www.w3.org/2001/XMLSchema#decimal">505494</literal>
      </binding>
    </result>
    <result>
      <binding name="refArea">
        <uri>http://worldbank.270a.info/classification/country/KZ</uri>
      </binding>
      <binding name="obsValue">
        <literal datatype="http://www.w3.org/2001/XMLSchema#decimal">146904</literal>
      </binding>
    </result>
    <result>
      <binding name="refArea">
        <uri>http://worldbank.270a.info/classification/country/KE</uri>
      </binding>
      <binding name="obsValue">
        <literal datatype="http://www.w3.org/2001/XMLSchema#decimal">686731</literal>
      </binding>
    </result>
    <result>
      <binding name="refArea">
        <uri>http://worldbank.270a.info/classification/country/KG</uri>
      </binding>
      <binding name="obsValue">
        <literal datatype="http://www.w3.org/2001/XMLSchema#decimal">53332</literal>
      </binding>
    </result>
    <result>
      <binding name="refArea">
        <uri>http://worldbank.270a.info/classification/country/KH</uri>
      </binding>
      <binding name="obsValue">
        <literal datatype="http://www.w3.org/2001/XMLSchema#decimal">176141</literal>
      </binding>
    </result>
    <result>
      <binding name="refArea">
        <uri>http://worldbank.270a.info/classification/country/KR</uri>
      </binding>
      <binding name="obsValue">
        <literal datatype="http://www.w3.org/2001/XMLSchema#decimal">206095</literal>
      </binding>
    </result>
    <result>
      <binding name="refArea">
        <uri>http://worldbank.270a.info/classification/country/KW</uri>
      </binding>
      <binding name="obsValue">
        <literal datatype="http://www.w3.org/2001/XMLSchema#decimal">25840</literal>
      </binding>
    </result>
    <result>
      <binding name="refArea">
        <uri>http://worldbank.270a.info/classification/country/LA</uri>
      </binding>
      <binding name="obsValue">
        <literal datatype="http://www.w3.org/2001/XMLSchema#decimal">72263</literal>
      </binding>
    </result>
    <result>
      <binding name="refArea">
        <uri>http://worldbank.270a.info/classification/country/LB</uri>
      </binding>
      <binding name="obsValue">
        <literal datatype="http://www.w3.org/2001/XMLSchema#decimal">35232</literal>
      </binding>
    </result>
    <result>
      <binding name="refArea">
        <uri>http://worldbank.270a.info/classification/country/LR</uri>
      </binding>
      <binding name="obsValue">
        <literal datatype="http://www.w3.org/2001/XMLSchema#decimal">82977</literal>
      </binding>
    </result>
    <result>
      <binding name="refArea">
        <uri>http://worldbank.270a.info/classification/country/LY</uri>
      </binding>
      <binding name="obsValue">
        <literal datatype="http://www.w3.org/2001/XMLSchema#decimal">70608</literal>
      </binding>
    </result>
    <result>
      <binding name="refArea">
        <uri>http://worldbank.270a.info/classification/country/LC</uri>
      </binding>
      <binding name="obsValue">
        <literal datatype="http://www.w3.org/2001/XMLSchema#decimal">1556</literal>
      </binding>
    </result>
    <result>
      <binding name="refArea">
        <uri>http://worldbank.270a.info/classification/country/LK</uri>
      </binding>
      <binding name="obsValue">
        <literal datatype="http://www.w3.org/2001/XMLSchema#decimal">138488</literal>
      </binding>
    </result>
    <result>
      <binding name="refArea">
        <uri>http://worldbank.270a.info/classification/country/LS</uri>
      </binding>
      <binding name="obsValue">
        <literal datatype="http://www.w3.org/2001/XMLSchema#decimal">26141</literal>
      </binding>
    </result>
    <result>
      <binding name="refArea">
        <uri>http://worldbank.270a.info/classification/country/LT</uri>
      </binding>
      <binding name="obsValue">
        <literal datatype="http://www.w3.org/2001/XMLSchema#decimal">14719</literal>
      </binding>
    </result>
    <result>
      <binding name="refArea">
        <uri>http://worldbank.270a.info/classification/country/LU</uri>
      </binding>
      <binding name="obsValue">
        <literal datatype="http://www.w3.org/2001/XMLSchema#decimal">2726</literal>
      </binding>
    </result>
    <result>
      <binding name="refArea">
        <uri>http://worldbank.270a.info/classification/country/LV</uri>
      </binding>
      <binding name="obsValue">
        <literal datatype="http://www.w3.org/2001/XMLSchema#decimal">10502</literal>
      </binding>
    </result>
    <result>
      <binding name="refArea">
        <uri>http://worldbank.270a.info/classification/country/MO</uri>
      </binding>
      <binding name="obsValue">
        <literal datatype="http://www.w3.org/2001/XMLSchema#decimal">1813</literal>
      </binding>
    </result>
    <result>
      <binding name="refArea">
        <uri>http://worldbank.270a.info/classification/country/MA</uri>
      </binding>
      <binding name="obsValue">
        <literal datatype="http://www.w3.org/2001/XMLSchema#decimal">305421</literal>
      </binding>
    </result>
    <result>
      <binding name="refArea">
        <uri>http://worldbank.270a.info/classification/country/MD</uri>
      </binding>
      <binding name="obsValue">
        <literal datatype="http://www.w3.org/2001/XMLSchema#decimal">20136</literal>
      </binding>
    </result>
    <result>
      <binding name="refArea">
        <uri>http://worldbank.270a.info/classification/country/MG</uri>
      </binding>
      <binding name="obsValue">
        <literal datatype="http://www.w3.org/2001/XMLSchema#decimal">329797</literal>
      </binding>
    </result>
    <result>
      <binding name="refArea">
        <uri>http://worldbank.270a.info/classification/country/MV</uri>
      </binding>
      <binding name="obsValue">
        <literal datatype="http://www.w3.org/2001/XMLSchema#decimal">3478</literal>
      </binding>
    </result>
    <result>
      <binding name="refArea">
        <uri>http://worldbank.270a.info/classification/country/MX</uri>
      </binding>
      <binding name="obsValue">
        <literal datatype="http://www.w3.org/2001/XMLSchema#decimal">963968</literal>
      </binding>
    </result>
    <result>
      <binding name="refArea">
        <uri>http://worldbank.270a.info/classification/country/MK</uri>
      </binding>
      <binding name="obsValue">
        <literal datatype="http://www.w3.org/2001/XMLSchema#decimal">10380</literal>
      </binding>
    </result>
    <result>
      <binding name="refArea">
        <uri>http://worldbank.270a.info/classification/country/ML</uri>
      </binding>
      <binding name="obsValue">
        <literal datatype="http://www.w3.org/2001/XMLSchema#decimal">251055</literal>
      </binding>
    </result>
    <result>
      <binding name="refArea">
        <uri>http://worldbank.270a.info/classification/country/MT</uri>
      </binding>
      <binding name="obsValue">
        <literal datatype="http://www.w3.org/2001/XMLSchema#decimal">1931</literal>
      </binding>
    </result>
    <result>
      <binding name="refArea">
        <uri>http://worldbank.270a.info/classification/country/MM</uri>
      </binding>
      <binding name="obsValue">
        <literal datatype="http://www.w3.org/2001/XMLSchema#decimal">396081</literal>
      </binding>
    </result>
    <result>
      <binding name="refArea">
        <uri>http://worldbank.270a.info/classification/country/MN</uri>
      </binding>
      <binding name="obsValue">
        <literal datatype="http://www.w3.org/2001/XMLSchema#decimal">22868</literal>
      </binding>
    </result>
    <result>
      <binding name="refArea">
        <uri>http://worldbank.270a.info/classification/country/MZ</uri>
      </binding>
      <binding name="obsValue">
        <literal datatype="http://www.w3.org/2001/XMLSchema#decimal">365928</literal>
      </binding>
    </result>
    <result>
      <binding name="refArea">
        <uri>http://worldbank.270a.info/classification/country/MR</uri>
      </binding>
      <binding name="obsValue">
        <literal datatype="http://www.w3.org/2001/XMLSchema#decimal">46076</literal>
      </binding>
    </result>
    <result>
      <binding name="refArea">
        <uri>http://worldbank.270a.info/classification/country/MU</uri>
      </binding>
      <binding name="obsValue">
        <literal datatype="http://www.w3.org/2001/XMLSchema#decimal">9082</literal>
      </binding>
    </result>
    <result>
      <binding name="refArea">
        <uri>http://worldbank.270a.info/classification/country/MW</uri>
      </binding>
      <binding name="obsValue">
        <literal datatype="http://www.w3.org/2001/XMLSchema#decimal">254525</literal>
      </binding>
    </result>
    <result>
      <binding name="refArea">
        <uri>http://worldbank.270a.info/classification/country/MY</uri>
      </binding>
      <binding name="obsValue">
        <literal datatype="http://www.w3.org/2001/XMLSchema#decimal">267080</literal>
      </binding>
    </result>
    <result>
      <binding name="refArea">
        <uri>http://worldbank.270a.info/classification/country/NA</uri>
      </binding>
      <binding name="obsValue">
        <literal datatype="http://www.w3.org/2001/XMLSchema#decimal">25134</literal>
      </binding>
    </result>
    <result>
      <binding name="refArea">
        <uri>http://worldbank.270a.info/classification/country/NE</uri>
      </binding>
      <binding name="obsValue">
        <literal datatype="http://www.w3.org/2001/XMLSchema#decimal">297707</literal>
      </binding>
    </result>
    <result>
      <binding name="refArea">
        <uri>http://worldbank.270a.info/classification/country/NG</uri>
      </binding>
      <binding name="obsValue">
        <literal datatype="http://www.w3.org/2001/XMLSchema#decimal">2476684</literal>
      </binding>
    </result>
    <result>
      <binding name="refArea">
        <uri>http://worldbank.270a.info/classification/country/NI</uri>
      </binding>
      <binding name="obsValue">
        <literal datatype="http://www.w3.org/2001/XMLSchema#decimal">66419</literal>
      </binding>
    </result>
    <result>
      <binding name="refArea">
        <uri>http://worldbank.270a.info/classification/country/NL</uri>
      </binding>
      <binding name="obsValue">
        <literal datatype="http://www.w3.org/2001/XMLSchema#decimal">87530</literal>
      </binding>
    </result>
    <result>
      <binding name="refArea">
        <uri>http://worldbank.270a.info/classification/country/NO</uri>
      </binding>
      <binding name="obsValue">
        <literal datatype="http://www.w3.org/2001/XMLSchema#decimal">27788</literal>
      </binding>
    </result>
    <result>
      <binding name="refArea">
        <uri>http://worldbank.270a.info/classification/country/NP</uri>
      </binding>
      <binding name="obsValue">
        <literal datatype="http://www.w3.org/2001/XMLSchema#decimal">365063</literal>
      </binding>
    </result>
    <result>
      <binding name="refArea">
        <uri>http://worldbank.270a.info/classification/country/NZ</uri>
      </binding>
      <binding name="obsValue">
        <literal datatype="http://www.w3.org/2001/XMLSchema#decimal">27987</literal>
      </binding>
    </result>
    <result>
      <binding name="refArea">
        <uri>http://worldbank.270a.info/classification/country/OM</uri>
      </binding>
      <binding name="obsValue">
        <literal datatype="http://www.w3.org/2001/XMLSchema#decimal">28074</literal>
      </binding>
    </result>
    <result>
      <binding name="refArea">
        <uri>http://worldbank.270a.info/classification/country/PK</uri>
      </binding>
      <binding name="obsValue">
        <literal datatype="http://www.w3.org/2001/XMLSchema#decimal">1999627</literal>
      </binding>
    </result>
    <result>
      <binding name="refArea">
        <uri>http://worldbank.270a.info/classification/country/PA</uri>
      </binding>
      <binding name="obsValue">
        <literal datatype="http://www.w3.org/2001/XMLSchema#decimal">33631</literal>
      </binding>
    </result>
    <result>
      <binding name="refArea">
        <uri>http://worldbank.270a.info/classification/country/PE</uri>
      </binding>
      <binding name="obsValue">
        <literal datatype="http://www.w3.org/2001/XMLSchema#decimal">277788</literal>
      </binding>
    </result>
    <result>
      <binding name="refArea">
        <uri>http://worldbank.270a.info/classification/country/PH</uri>
      </binding>
      <binding name="obsValue">
        <literal datatype="http://www.w3.org/2001/XMLSchema#decimal">1093009</literal>
      </binding>
    </result>
    <result>
      <binding name="refArea">
        <uri>http://worldbank.270a.info/classification/country/PG</uri>
      </binding>
      <binding name="obsValue">
        <literal datatype="http://www.w3.org/2001/XMLSchema#decimal">83991</literal>
      </binding>
    </result>
    <result>
      <binding name="refArea">
        <uri>http://worldbank.270a.info/classification/country/PL</uri>
      </binding>
      <binding name="obsValue">
        <literal datatype="http://www.w3.org/2001/XMLSchema#decimal">174199</literal>
      </binding>
    </result>
    <result>
      <binding name="refArea">
        <uri>http://worldbank.270a.info/classification/country/KP</uri>
      </binding>
      <binding name="obsValue">
        <literal datatype="http://www.w3.org/2001/XMLSchema#decimal">141221</literal>
      </binding>
    </result>
    <result>
      <binding name="refArea">
        <uri>http://worldbank.270a.info/classification/country/PT</uri>
      </binding>
      <binding name="obsValue">
        <literal datatype="http://www.w3.org/2001/XMLSchema#decimal">53856</literal>
      </binding>
    </result>
    <result>
      <binding name="refArea">
        <uri>http://worldbank.270a.info/classification/country/PY</uri>
      </binding>
      <binding name="obsValue">
        <literal datatype="http://www.w3.org/2001/XMLSchema#decimal">72669</literal>
      </binding>
    </result>
    <result>
      <binding name="refArea">
        <uri>http://worldbank.270a.info/classification/country/QA</uri>
      </binding>
      <binding name="obsValue">
        <literal datatype="http://www.w3.org/2001/XMLSchema#decimal">6682</literal>
      </binding>
    </result>
    <result>
      <binding name="refArea">
        <uri>http://worldbank.270a.info/classification/country/RO</uri>
      </binding>
      <binding name="obsValue">
        <literal datatype="http://www.w3.org/2001/XMLSchema#decimal">97503</literal>
      </binding>
    </result>
    <result>
      <binding name="refArea">
        <uri>http://worldbank.270a.info/classification/country/RU</uri>
      </binding>
      <binding name="obsValue">
        <literal datatype="http://www.w3.org/2001/XMLSchema#decimal">739000</literal>
      </binding>
    </result>
    <result>
      <binding name="refArea">
        <uri>http://worldbank.270a.info/classification/country/RW</uri>
      </binding>
      <binding name="obsValue">
        <literal datatype="http://www.w3.org/2001/XMLSchema#decimal">190243</literal>
      </binding>
    </result>
    <result>
      <binding name="refArea">
        <uri>http://worldbank.270a.info/classification/country/SA</uri>
      </binding>
      <binding name="obsValue">
        <literal datatype="http://www.w3.org/2001/XMLSchema#decimal">303401</literal>
      </binding>
    </result>
    <result>
      <binding name="refArea">
        <uri>http://worldbank.270a.info/classification/country/SD</uri>
      </binding>
      <binding name="obsValue">
        <literal datatype="http://www.w3.org/2001/XMLSchema#decimal">550417</literal>
      </binding>
    </result>
    <result>
      <binding name="refArea">
        <uri>http://worldbank.270a.info/classification/country/SN</uri>
      </binding>
      <binding name="obsValue">
        <literal datatype="http://www.w3.org/2001/XMLSchema#decimal">197993</literal>
      </binding>
    </result>
    <result>
      <binding name="refArea">
        <uri>http://worldbank.270a.info/classification/country/SG</uri>
      </binding>
      <binding name="obsValue">
        <literal datatype="http://www.w3.org/2001/XMLSchema#decimal">17664</literal>
      </binding>
    </result>
    <result>
      <binding name="refArea">
        <uri>http://worldbank.270a.info/classification/country/SB</uri>
      </binding>
      <binding name="obsValue">
        <literal datatype="http://www.w3.org/2001/XMLSchema#decimal">6856</literal>
      </binding>
    </result>
    <result>
      <binding name="refArea">
        <uri>http://worldbank.270a.info/classification/country/SL</uri>
      </binding>
      <binding name="obsValue">
        <literal datatype="http://www.w3.org/2001/XMLSchema#decimal">102625</literal>
      </binding>
    </result>
    <result>
      <binding name="refArea">
        <uri>http://worldbank.270a.info/classification/country/SV</uri>
      </binding>
      <binding name="obsValue">
        <literal datatype="http://www.w3.org/2001/XMLSchema#decimal">73995</literal>
      </binding>
    </result>
    <result>
      <binding name="refArea">
        <uri>http://worldbank.270a.info/classification/country/SO</uri>
      </binding>
      <binding name="obsValue">
        <literal datatype="http://www.w3.org/2001/XMLSchema#decimal">159126</literal>
      </binding>
    </result>
    <result>
      <binding name="refArea">
        <uri>http://worldbank.270a.info/classification/country/ST</uri>
      </binding>
      <binding name="obsValue">
        <literal datatype="http://www.w3.org/2001/XMLSchema#decimal">2297</literal>
      </binding>
    </result>
    <result>
      <binding name="refArea">
        <uri>http://worldbank.270a.info/classification/country/SR</uri>
      </binding>
      <binding name="obsValue">
        <literal datatype="http://www.w3.org/2001/XMLSchema#decimal">4024</literal>
      </binding>
    </result>
    <result>
      <binding name="refArea">
        <uri>http://worldbank.270a.info/classification/country/SK</uri>
      </binding>
      <binding name="obsValue">
        <literal datatype="http://www.w3.org/2001/XMLSchema#decimal">25997</literal>
      </binding>
    </result>
    <result>
      <binding name="refArea">
        <uri>http://worldbank.270a.info/classification/country/SI</uri>
      </binding>
      <binding name="obsValue">
        <literal datatype="http://www.w3.org/2001/XMLSchema#decimal">8729</literal>
      </binding>
    </result>
    <result>
      <binding name="refArea">
        <uri>http://worldbank.270a.info/classification/country/SE</uri>
      </binding>
      <binding name="obsValue">
        <literal datatype="http://www.w3.org/2001/XMLSchema#decimal">52539</literal>
      </binding>
    </result>
    <result>
      <binding name="refArea">
        <uri>http://worldbank.270a.info/classification/country/SZ</uri>
      </binding>
      <binding name="obsValue">
        <literal datatype="http://www.w3.org/2001/XMLSchema#decimal">14618</literal>
      </binding>
    </result>
    <result>
      <binding name="refArea">
        <uri>http://worldbank.270a.info/classification/country/SY</uri>
      </binding>
      <binding name="obsValue">
        <literal datatype="http://www.w3.org/2001/XMLSchema#decimal">261283</literal>
      </binding>
    </result>
    <result>
      <binding name="refArea">
        <uri>http://worldbank.270a.info/classification/country/TD</uri>
      </binding>
      <binding name="obsValue">
        <literal datatype="http://www.w3.org/2001/XMLSchema#decimal">208053</literal>
      </binding>
    </result>
    <result>
      <binding name="refArea">
        <uri>http://worldbank.270a.info/classification/country/TG</uri>
      </binding>
      <binding name="obsValue">
        <literal datatype="http://www.w3.org/2001/XMLSchema#decimal">110082</literal>
      </binding>
    </result>
    <result>
      <binding name="refArea">
        <uri>http://worldbank.270a.info/classification/country/TH</uri>
      </binding>
      <binding name="obsValue">
        <literal datatype="http://www.w3.org/2001/XMLSchema#decimal">432391</literal>
      </binding>
    </result>
    <result>
      <binding name="refArea">
        <uri>http://worldbank.270a.info/classification/country/TJ</uri>
      </binding>
      <binding name="obsValue">
        <literal datatype="http://www.w3.org/2001/XMLSchema#decimal">84071</literal>
      </binding>
    </result>
    <result>
      <binding name="refArea">
        <uri>http://worldbank.270a.info/classification/country/TM</uri>
      </binding>
      <binding name="obsValue">
        <literal datatype="http://www.w3.org/2001/XMLSchema#decimal">49942</literal>
      </binding>
    </result>
    <result>
      <binding name="refArea">
        <uri>http://worldbank.270a.info/classification/country/TL</uri>
      </binding>
      <binding name="obsValue">
        <literal datatype="http://www.w3.org/2001/XMLSchema#decimal">22517</literal>
      </binding>
    </result>
    <result>
      <binding name="refArea">
        <uri>http://worldbank.270a.info/classification/country/TO</uri>
      </binding>
      <binding name="obsValue">
        <literal datatype="http://www.w3.org/2001/XMLSchema#decimal">1164</literal>
      </binding>
    </result>
    <result>
      <binding name="refArea">
        <uri>http://worldbank.270a.info/classification/country/TT</uri>
      </binding>
      <binding name="obsValue">
        <literal datatype="http://www.w3.org/2001/XMLSchema#decimal">9579</literal>
      </binding>
    </result>
    <result>
      <binding name="refArea">
        <uri>http://worldbank.270a.info/classification/country/TN</uri>
      </binding>
      <binding name="obsValue">
        <literal datatype="http://www.w3.org/2001/XMLSchema#decimal">83024</literal>
      </binding>
    </result>
    <result>
      <binding name="refArea">
        <uri>http://worldbank.270a.info/classification/country/TR</uri>
      </binding>
      <binding name="obsValue">
        <literal datatype="http://www.w3.org/2001/XMLSchema#decimal">654198</literal>
      </binding>
    </result>
    <result>
      <binding name="refArea">
        <uri>http://worldbank.270a.info/classification/country/TZ</uri>
      </binding>
      <binding name="obsValue">
        <literal datatype="http://www.w3.org/2001/XMLSchema#decimal">719117</literal>
      </binding>
    </result>
    <result>
      <binding name="refArea">
        <uri>http://worldbank.270a.info/classification/country/UG</uri>
      </binding>
      <binding name="obsValue">
        <literal datatype="http://www.w3.org/2001/XMLSchema#decimal">659296</literal>
      </binding>
    </result>
    <result>
      <binding name="refArea">
        <uri>http://worldbank.270a.info/classification/country/UA</uri>
      </binding>
      <binding name="obsValue">
        <literal datatype="http://www.w3.org/2001/XMLSchema#decimal">203646</literal>
      </binding>
    </result>
    <result>
      <binding name="refArea">
        <uri>http://worldbank.270a.info/classification/country/UY</uri>
      </binding>
      <binding name="obsValue">
        <literal datatype="http://www.w3.org/2001/XMLSchema#decimal">23860</literal>
      </binding>
    </result>
    <result>
      <binding name="refArea">
        <uri>http://worldbank.270a.info/classification/country/US</uri>
      </binding>
      <binding name="obsValue">
        <literal datatype="http://www.w3.org/2001/XMLSchema#decimal">2119454</literal>
      </binding>
    </result>
    <result>
      <binding name="refArea">
        <uri>http://worldbank.270a.info/classification/country/UZ</uri>
      </binding>
      <binding name="obsValue">
        <literal datatype="http://www.w3.org/2001/XMLSchema#decimal">290460</literal>
      </binding>
    </result>
    <result>
      <binding name="refArea">
        <uri>http://worldbank.270a.info/classification/country/VC</uri>
      </binding>
      <binding name="obsValue">
        <literal datatype="http://www.w3.org/2001/XMLSchema#decimal">1156</literal>
      </binding>
    </result>
    <result>
      <binding name="refArea">
        <uri>http://worldbank.270a.info/classification/country/VE</uri>
      </binding>
      <binding name="obsValue">
        <literal datatype="http://www.w3.org/2001/XMLSchema#decimal">287790</literal>
      </binding>
    </result>
    <result>
      <binding name="refArea">
        <uri>http://worldbank.270a.info/classification/country/VN</uri>
      </binding>
      <binding name="obsValue">
        <literal datatype="http://www.w3.org/2001/XMLSchema#decimal">801354</literal>
      </binding>
    </result>
    <result>
      <binding name="refArea">
        <uri>http://worldbank.270a.info/classification/country/VU</uri>
      </binding>
      <binding name="obsValue">
        <literal datatype="http://www.w3.org/2001/XMLSchema#decimal">3112</literal>
      </binding>
    </result>
    <result>
      <binding name="refArea">
        <uri>http://worldbank.270a.info/classification/country/PS</uri>
      </binding>
      <binding name="obsValue">
        <literal datatype="http://www.w3.org/2001/XMLSchema#decimal">70816</literal>
      </binding>
    </result>
    <result>
      <binding name="refArea">
        <uri>http://worldbank.270a.info/classification/country/WS</uri>
      </binding>
      <binding name="obsValue">
        <literal datatype="http://www.w3.org/2001/XMLSchema#decimal">2073</literal>
      </binding>
    </result>
    <result>
      <binding name="refArea">
        <uri>http://worldbank.270a.info/classification/country/YE</uri>
      </binding>
      <binding name="obsValue">
        <literal datatype="http://www.w3.org/2001/XMLSchema#decimal">404347</literal>
      </binding>
    </result>
    <result>
      <binding name="refArea">
        <uri>http://worldbank.270a.info/classification/country/ZA</uri>
      </binding>
      <binding name="obsValue">
        <literal datatype="http://www.w3.org/2001/XMLSchema#decimal">504380</literal>
      </binding>
    </result>
    <result>
      <binding name="refArea">
        <uri>http://worldbank.270a.info/classification/country/CD</uri>
      </binding>
      <binding name="obsValue">
        <literal datatype="http://www.w3.org/2001/XMLSchema#decimal">1342417</literal>
      </binding>
    </result>
    <result>
      <binding name="refArea">
        <uri>http://worldbank.270a.info/classification/country/ZM</uri>
      </binding>
      <binding name="obsValue">
        <literal datatype="http://www.w3.org/2001/XMLSchema#decimal">203277</literal>
      </binding>
    </result>
    <result>
      <binding name="refArea">
        <uri>http://worldbank.270a.info/classification/country/ZW</uri>
      </binding>
      <binding name="obsValue">
        <literal datatype="http://www.w3.org/2001/XMLSchema#decimal">170937</literal>
      </binding>
    </result>
  </results>
</sparql>
