<?xml version="1.0"?>
<sparql xmlns="http://www.w3.org/2005/sparql-results#">
  <head>
    <variable name="refArea"/>
    <variable name="obsValue"/>
  </head>
  <results>
    <result>
      <binding name="refArea">
        <uri>http://worldbank.270a.info/classification/country/AW</uri>
      </binding>
      <binding name="obsValue">
        <literal datatype="http://www.w3.org/2001/XMLSchema#decimal">3617</literal>
      </binding>
    </result>
    <result>
      <binding name="refArea">
        <uri>http://worldbank.270a.info/classification/country/AF</uri>
      </binding>
      <binding name="obsValue">
        <literal datatype="http://www.w3.org/2001/XMLSchema#decimal">2022213</literal>
      </binding>
    </result>
    <result>
      <binding name="refArea">
        <uri>http://worldbank.270a.info/classification/country/AO</uri>
      </binding>
      <binding name="obsValue">
        <literal datatype="http://www.w3.org/2001/XMLSchema#decimal">1224768</literal>
      </binding>
    </result>
    <result>
      <binding name="refArea">
        <uri>http://worldbank.270a.info/classification/country/AL</uri>
      </binding>
      <binding name="obsValue">
        <literal datatype="http://www.w3.org/2001/XMLSchema#decimal">123486</literal>
      </binding>
    </result>
    <result>
      <binding name="refArea">
        <uri>http://worldbank.270a.info/classification/country/AE</uri>
      </binding>
      <binding name="obsValue">
        <literal datatype="http://www.w3.org/2001/XMLSchema#decimal">139270</literal>
      </binding>
    </result>
    <result>
      <binding name="refArea">
        <uri>http://worldbank.270a.info/classification/country/AR</uri>
      </binding>
      <binding name="obsValue">
        <literal datatype="http://www.w3.org/2001/XMLSchema#decimal">1657870</literal>
      </binding>
    </result>
    <result>
      <binding name="refArea">
        <uri>http://worldbank.270a.info/classification/country/AM</uri>
      </binding>
      <binding name="obsValue">
        <literal datatype="http://www.w3.org/2001/XMLSchema#decimal">79070</literal>
      </binding>
    </result>
    <result>
      <binding name="refArea">
        <uri>http://worldbank.270a.info/classification/country/AU</uri>
      </binding>
      <binding name="obsValue">
        <literal datatype="http://www.w3.org/2001/XMLSchema#decimal">655120</literal>
      </binding>
    </result>
    <result>
      <binding name="refArea">
        <uri>http://worldbank.270a.info/classification/country/AT</uri>
      </binding>
      <binding name="obsValue">
        <literal datatype="http://www.w3.org/2001/XMLSchema#decimal">209471</literal>
      </binding>
    </result>
    <result>
      <binding name="refArea">
        <uri>http://worldbank.270a.info/classification/country/AZ</uri>
      </binding>
      <binding name="obsValue">
        <literal datatype="http://www.w3.org/2001/XMLSchema#decimal">278890</literal>
      </binding>
    </result>
    <result>
      <binding name="refArea">
        <uri>http://worldbank.270a.info/classification/country/BI</uri>
      </binding>
      <binding name="obsValue">
        <literal datatype="http://www.w3.org/2001/XMLSchema#decimal">576937</literal>
      </binding>
    </result>
    <result>
      <binding name="refArea">
        <uri>http://worldbank.270a.info/classification/country/BE</uri>
      </binding>
      <binding name="obsValue">
        <literal datatype="http://www.w3.org/2001/XMLSchema#decimal">288564</literal>
      </binding>
    </result>
    <result>
      <binding name="refArea">
        <uri>http://worldbank.270a.info/classification/country/BJ</uri>
      </binding>
      <binding name="obsValue">
        <literal datatype="http://www.w3.org/2001/XMLSchema#decimal">629894</literal>
      </binding>
    </result>
    <result>
      <binding name="refArea">
        <uri>http://worldbank.270a.info/classification/country/BF</uri>
      </binding>
      <binding name="obsValue">
        <literal datatype="http://www.w3.org/2001/XMLSchema#decimal">1064460</literal>
      </binding>
    </result>
    <result>
      <binding name="refArea">
        <uri>http://worldbank.270a.info/classification/country/BD</uri>
      </binding>
      <binding name="obsValue">
        <literal datatype="http://www.w3.org/2001/XMLSchema#decimal">8777471</literal>
      </binding>
    </result>
    <result>
      <binding name="refArea">
        <uri>http://worldbank.270a.info/classification/country/BG</uri>
      </binding>
      <binding name="obsValue">
        <literal datatype="http://www.w3.org/2001/XMLSchema#decimal">158131</literal>
      </binding>
    </result>
    <result>
      <binding name="refArea">
        <uri>http://worldbank.270a.info/classification/country/BH</uri>
      </binding>
      <binding name="obsValue">
        <literal datatype="http://www.w3.org/2001/XMLSchema#decimal">30788</literal>
      </binding>
    </result>
    <result>
      <binding name="refArea">
        <uri>http://worldbank.270a.info/classification/country/BS</uri>
      </binding>
      <binding name="obsValue">
        <literal datatype="http://www.w3.org/2001/XMLSchema#decimal">14464</literal>
      </binding>
    </result>
    <result>
      <binding name="refArea">
        <uri>http://worldbank.270a.info/classification/country/BA</uri>
      </binding>
      <binding name="obsValue">
        <literal datatype="http://www.w3.org/2001/XMLSchema#decimal">111401</literal>
      </binding>
    </result>
    <result>
      <binding name="refArea">
        <uri>http://worldbank.270a.info/classification/country/BY</uri>
      </binding>
      <binding name="obsValue">
        <literal datatype="http://www.w3.org/2001/XMLSchema#decimal">222100</literal>
      </binding>
    </result>
    <result>
      <binding name="refArea">
        <uri>http://worldbank.270a.info/classification/country/BZ</uri>
      </binding>
      <binding name="obsValue">
        <literal datatype="http://www.w3.org/2001/XMLSchema#decimal">17443</literal>
      </binding>
    </result>
    <result>
      <binding name="refArea">
        <uri>http://worldbank.270a.info/classification/country/BO</uri>
      </binding>
      <binding name="obsValue">
        <literal datatype="http://www.w3.org/2001/XMLSchema#decimal">567471</literal>
      </binding>
    </result>
    <result>
      <binding name="refArea">
        <uri>http://worldbank.270a.info/classification/country/BR</uri>
      </binding>
      <binding name="obsValue">
        <literal datatype="http://www.w3.org/2001/XMLSchema#decimal">8630042</literal>
      </binding>
    </result>
    <result>
      <binding name="refArea">
        <uri>http://worldbank.270a.info/classification/country/BB</uri>
      </binding>
      <binding name="obsValue">
        <literal datatype="http://www.w3.org/2001/XMLSchema#decimal">8616</literal>
      </binding>
    </result>
    <result>
      <binding name="refArea">
        <uri>http://worldbank.270a.info/classification/country/BN</uri>
      </binding>
      <binding name="obsValue">
        <literal datatype="http://www.w3.org/2001/XMLSchema#decimal">17191</literal>
      </binding>
    </result>
    <result>
      <binding name="refArea">
        <uri>http://worldbank.270a.info/classification/country/BT</uri>
      </binding>
      <binding name="obsValue">
        <literal datatype="http://www.w3.org/2001/XMLSchema#decimal">32781</literal>
      </binding>
    </result>
    <result>
      <binding name="refArea">
        <uri>http://worldbank.270a.info/classification/country/BW</uri>
      </binding>
      <binding name="obsValue">
        <literal datatype="http://www.w3.org/2001/XMLSchema#decimal">105350</literal>
      </binding>
    </result>
    <result>
      <binding name="refArea">
        <uri>http://worldbank.270a.info/classification/country/CF</uri>
      </binding>
      <binding name="obsValue">
        <literal datatype="http://www.w3.org/2001/XMLSchema#decimal">298084</literal>
      </binding>
    </result>
    <result>
      <binding name="refArea">
        <uri>http://worldbank.270a.info/classification/country/CA</uri>
      </binding>
      <binding name="obsValue">
        <literal datatype="http://www.w3.org/2001/XMLSchema#decimal">935147</literal>
      </binding>
    </result>
    <result>
      <binding name="refArea">
        <uri>http://worldbank.270a.info/classification/country/CH</uri>
      </binding>
      <binding name="obsValue">
        <literal datatype="http://www.w3.org/2001/XMLSchema#decimal">203147</literal>
      </binding>
    </result>
    <result>
      <binding name="refArea">
        <uri>http://worldbank.270a.info/classification/country/CL</uri>
      </binding>
      <binding name="obsValue">
        <literal datatype="http://www.w3.org/2001/XMLSchema#decimal">629078</literal>
      </binding>
    </result>
    <result>
      <binding name="refArea">
        <uri>http://worldbank.270a.info/classification/country/CN</uri>
      </binding>
      <binding name="obsValue">
        <literal datatype="http://www.w3.org/2001/XMLSchema#decimal">41783239</literal>
      </binding>
    </result>
    <result>
      <binding name="refArea">
        <uri>http://worldbank.270a.info/classification/country/CI</uri>
      </binding>
      <binding name="obsValue">
        <literal datatype="http://www.w3.org/2001/XMLSchema#decimal">1279115</literal>
      </binding>
    </result>
    <result>
      <binding name="refArea">
        <uri>http://worldbank.270a.info/classification/country/CM</uri>
      </binding>
      <binding name="obsValue">
        <literal datatype="http://www.w3.org/2001/XMLSchema#decimal">1224230</literal>
      </binding>
    </result>
    <result>
      <binding name="refArea">
        <uri>http://worldbank.270a.info/classification/country/CG</uri>
      </binding>
      <binding name="obsValue">
        <literal datatype="http://www.w3.org/2001/XMLSchema#decimal">257817</literal>
      </binding>
    </result>
    <result>
      <binding name="refArea">
        <uri>http://worldbank.270a.info/classification/country/CO</uri>
      </binding>
      <binding name="obsValue">
        <literal datatype="http://www.w3.org/2001/XMLSchema#decimal">2216718</literal>
      </binding>
    </result>
    <result>
      <binding name="refArea">
        <uri>http://worldbank.270a.info/classification/country/KM</uri>
      </binding>
      <binding name="obsValue">
        <literal datatype="http://www.w3.org/2001/XMLSchema#decimal">56788</literal>
      </binding>
    </result>
    <result>
      <binding name="refArea">
        <uri>http://worldbank.270a.info/classification/country/CV</uri>
      </binding>
      <binding name="obsValue">
        <literal datatype="http://www.w3.org/2001/XMLSchema#decimal">33246</literal>
      </binding>
    </result>
    <result>
      <binding name="refArea">
        <uri>http://worldbank.270a.info/classification/country/CR</uri>
      </binding>
      <binding name="obsValue">
        <literal datatype="http://www.w3.org/2001/XMLSchema#decimal">196357</literal>
      </binding>
    </result>
    <result>
      <binding name="refArea">
        <uri>http://worldbank.270a.info/classification/country/CU</uri>
      </binding>
      <binding name="obsValue">
        <literal datatype="http://www.w3.org/2001/XMLSchema#decimal">327990</literal>
      </binding>
    </result>
    <result>
      <binding name="refArea">
        <uri>http://worldbank.270a.info/classification/country/CY</uri>
      </binding>
      <binding name="obsValue">
        <literal datatype="http://www.w3.org/2001/XMLSchema#decimal">25501</literal>
      </binding>
    </result>
    <result>
      <binding name="refArea">
        <uri>http://worldbank.270a.info/classification/country/CZ</uri>
      </binding>
      <binding name="obsValue">
        <literal datatype="http://www.w3.org/2001/XMLSchema#decimal">220369</literal>
      </binding>
    </result>
    <result>
      <binding name="refArea">
        <uri>http://worldbank.270a.info/classification/country/DE</uri>
      </binding>
      <binding name="obsValue">
        <literal datatype="http://www.w3.org/2001/XMLSchema#decimal">1904053</literal>
      </binding>
    </result>
    <result>
      <binding name="refArea">
        <uri>http://worldbank.270a.info/classification/country/DJ</uri>
      </binding>
      <binding name="obsValue">
        <literal datatype="http://www.w3.org/2001/XMLSchema#decimal">50092</literal>
      </binding>
    </result>
    <result>
      <binding name="refArea">
        <uri>http://worldbank.270a.info/classification/country/DK</uri>
      </binding>
      <binding name="obsValue">
        <literal datatype="http://www.w3.org/2001/XMLSchema#decimal">165224</literal>
      </binding>
    </result>
    <result>
      <binding name="refArea">
        <uri>http://worldbank.270a.info/classification/country/DO</uri>
      </binding>
      <binding name="obsValue">
        <literal datatype="http://www.w3.org/2001/XMLSchema#decimal">523657</literal>
      </binding>
    </result>
    <result>
      <binding name="refArea">
        <uri>http://worldbank.270a.info/classification/country/DZ</uri>
      </binding>
      <binding name="obsValue">
        <literal datatype="http://www.w3.org/2001/XMLSchema#decimal">1465954</literal>
      </binding>
    </result>
    <result>
      <binding name="refArea">
        <uri>http://worldbank.270a.info/classification/country/EC</uri>
      </binding>
      <binding name="obsValue">
        <literal datatype="http://www.w3.org/2001/XMLSchema#decimal">697723</literal>
      </binding>
    </result>
    <result>
      <binding name="refArea">
        <uri>http://worldbank.270a.info/classification/country/EG</uri>
      </binding>
      <binding name="obsValue">
        <literal datatype="http://www.w3.org/2001/XMLSchema#decimal">4010997</literal>
      </binding>
    </result>
    <result>
      <binding name="refArea">
        <uri>http://worldbank.270a.info/classification/country/ER</uri>
      </binding>
      <binding name="obsValue">
        <literal datatype="http://www.w3.org/2001/XMLSchema#decimal">334485</literal>
      </binding>
    </result>
    <result>
      <binding name="refArea">
        <uri>http://worldbank.270a.info/classification/country/ES</uri>
      </binding>
      <binding name="obsValue">
        <literal datatype="http://www.w3.org/2001/XMLSchema#decimal">1034690</literal>
      </binding>
    </result>
    <result>
      <binding name="refArea">
        <uri>http://worldbank.270a.info/classification/country/EE</uri>
      </binding>
      <binding name="obsValue">
        <literal datatype="http://www.w3.org/2001/XMLSchema#decimal">30214</literal>
      </binding>
    </result>
    <result>
      <binding name="refArea">
        <uri>http://worldbank.270a.info/classification/country/ET</uri>
      </binding>
      <binding name="obsValue">
        <literal datatype="http://www.w3.org/2001/XMLSchema#decimal">5849195</literal>
      </binding>
    </result>
    <result>
      <binding name="refArea">
        <uri>http://worldbank.270a.info/classification/country/FI</uri>
      </binding>
      <binding name="obsValue">
        <literal datatype="http://www.w3.org/2001/XMLSchema#decimal">144231</literal>
      </binding>
    </result>
    <result>
      <binding name="refArea">
        <uri>http://worldbank.270a.info/classification/country/FJ</uri>
      </binding>
      <binding name="obsValue">
        <literal datatype="http://www.w3.org/2001/XMLSchema#decimal">42854</literal>
      </binding>
    </result>
    <result>
      <binding name="refArea">
        <uri>http://worldbank.270a.info/classification/country/FR</uri>
      </binding>
      <binding name="obsValue">
        <literal datatype="http://www.w3.org/2001/XMLSchema#decimal">1877536</literal>
      </binding>
    </result>
    <result>
      <binding name="refArea">
        <uri>http://worldbank.270a.info/classification/country/FM</uri>
      </binding>
      <binding name="obsValue">
        <literal datatype="http://www.w3.org/2001/XMLSchema#decimal">6761</literal>
      </binding>
    </result>
    <result>
      <binding name="refArea">
        <uri>http://worldbank.270a.info/classification/country/GA</uri>
      </binding>
      <binding name="obsValue">
        <literal datatype="http://www.w3.org/2001/XMLSchema#decimal">74748</literal>
      </binding>
    </result>
    <result>
      <binding name="refArea">
        <uri>http://worldbank.270a.info/classification/country/GB</uri>
      </binding>
      <binding name="obsValue">
        <literal datatype="http://www.w3.org/2001/XMLSchema#decimal">1708192</literal>
      </binding>
    </result>
    <result>
      <binding name="refArea">
        <uri>http://worldbank.270a.info/classification/country/GE</uri>
      </binding>
      <binding name="obsValue">
        <literal datatype="http://www.w3.org/2001/XMLSchema#decimal">115604</literal>
      </binding>
    </result>
    <result>
      <binding name="refArea">
        <uri>http://worldbank.270a.info/classification/country/GH</uri>
      </binding>
      <binding name="obsValue">
        <literal datatype="http://www.w3.org/2001/XMLSchema#decimal">1431878</literal>
      </binding>
    </result>
    <result>
      <binding name="refArea">
        <uri>http://worldbank.270a.info/classification/country/GN</uri>
      </binding>
      <binding name="obsValue">
        <literal datatype="http://www.w3.org/2001/XMLSchema#decimal">635259</literal>
      </binding>
    </result>
    <result>
      <binding name="refArea">
        <uri>http://worldbank.270a.info/classification/country/GM</uri>
      </binding>
      <binding name="obsValue">
        <literal datatype="http://www.w3.org/2001/XMLSchema#decimal">113661</literal>
      </binding>
    </result>
    <result>
      <binding name="refArea">
        <uri>http://worldbank.270a.info/classification/country/GW</uri>
      </binding>
      <binding name="obsValue">
        <literal datatype="http://www.w3.org/2001/XMLSchema#decimal">126020</literal>
      </binding>
    </result>
    <result>
      <binding name="refArea">
        <uri>http://worldbank.270a.info/classification/country/GQ</uri>
      </binding>
      <binding name="obsValue">
        <literal datatype="http://www.w3.org/2001/XMLSchema#decimal">34439</literal>
      </binding>
    </result>
    <result>
      <binding name="refArea">
        <uri>http://worldbank.270a.info/classification/country/GR</uri>
      </binding>
      <binding name="obsValue">
        <literal datatype="http://www.w3.org/2001/XMLSchema#decimal">254830</literal>
      </binding>
    </result>
    <result>
      <binding name="refArea">
        <uri>http://worldbank.270a.info/classification/country/GD</uri>
      </binding>
      <binding name="obsValue">
        <literal datatype="http://www.w3.org/2001/XMLSchema#decimal">5551</literal>
      </binding>
    </result>
    <result>
      <binding name="refArea">
        <uri>http://worldbank.270a.info/classification/country/GT</uri>
      </binding>
      <binding name="obsValue">
        <literal datatype="http://www.w3.org/2001/XMLSchema#decimal">929329</literal>
      </binding>
    </result>
    <result>
      <binding name="refArea">
        <uri>http://worldbank.270a.info/classification/country/GY</uri>
      </binding>
      <binding name="obsValue">
        <literal datatype="http://www.w3.org/2001/XMLSchema#decimal">38785</literal>
      </binding>
    </result>
    <result>
      <binding name="refArea">
        <uri>http://worldbank.270a.info/classification/country/HK</uri>
      </binding>
      <binding name="obsValue">
        <literal datatype="http://www.w3.org/2001/XMLSchema#decimal">179060</literal>
      </binding>
    </result>
    <result>
      <binding name="refArea">
        <uri>http://worldbank.270a.info/classification/country/HN</uri>
      </binding>
      <binding name="obsValue">
        <literal datatype="http://www.w3.org/2001/XMLSchema#decimal">442865</literal>
      </binding>
    </result>
    <result>
      <binding name="refArea">
        <uri>http://worldbank.270a.info/classification/country/HR</uri>
      </binding>
      <binding name="obsValue">
        <literal datatype="http://www.w3.org/2001/XMLSchema#decimal">109934</literal>
      </binding>
    </result>
    <result>
      <binding name="refArea">
        <uri>http://worldbank.270a.info/classification/country/HT</uri>
      </binding>
      <binding name="obsValue">
        <literal datatype="http://www.w3.org/2001/XMLSchema#decimal">566792</literal>
      </binding>
    </result>
    <result>
      <binding name="refArea">
        <uri>http://worldbank.270a.info/classification/country/HU</uri>
      </binding>
      <binding name="obsValue">
        <literal datatype="http://www.w3.org/2001/XMLSchema#decimal">240068</literal>
      </binding>
    </result>
    <result>
      <binding name="refArea">
        <uri>http://worldbank.270a.info/classification/country/ID</uri>
      </binding>
      <binding name="obsValue">
        <literal datatype="http://www.w3.org/2001/XMLSchema#decimal">10481161</literal>
      </binding>
    </result>
    <result>
      <binding name="refArea">
        <uri>http://worldbank.270a.info/classification/country/IN</uri>
      </binding>
      <binding name="obsValue">
        <literal datatype="http://www.w3.org/2001/XMLSchema#decimal">59022594</literal>
      </binding>
    </result>
    <result>
      <binding name="refArea">
        <uri>http://worldbank.270a.info/classification/country/IE</uri>
      </binding>
      <binding name="obsValue">
        <literal datatype="http://www.w3.org/2001/XMLSchema#decimal">147367</literal>
      </binding>
    </result>
    <result>
      <binding name="refArea">
        <uri>http://worldbank.270a.info/classification/country/IR</uri>
      </binding>
      <binding name="obsValue">
        <literal datatype="http://www.w3.org/2001/XMLSchema#decimal">2743363</literal>
      </binding>
    </result>
    <result>
      <binding name="refArea">
        <uri>http://worldbank.270a.info/classification/country/IQ</uri>
      </binding>
      <binding name="obsValue">
        <literal datatype="http://www.w3.org/2001/XMLSchema#decimal">1954499</literal>
      </binding>
    </result>
    <result>
      <binding name="refArea">
        <uri>http://worldbank.270a.info/classification/country/IS</uri>
      </binding>
      <binding name="obsValue">
        <literal datatype="http://www.w3.org/2001/XMLSchema#decimal">10325</literal>
      </binding>
    </result>
    <result>
      <binding name="refArea">
        <uri>http://worldbank.270a.info/classification/country/IL</uri>
      </binding>
      <binding name="obsValue">
        <literal datatype="http://www.w3.org/2001/XMLSchema#decimal">319977</literal>
      </binding>
    </result>
    <result>
      <binding name="refArea">
        <uri>http://worldbank.270a.info/classification/country/IT</uri>
      </binding>
      <binding name="obsValue">
        <literal datatype="http://www.w3.org/2001/XMLSchema#decimal">1323486</literal>
      </binding>
    </result>
    <result>
      <binding name="refArea">
        <uri>http://worldbank.270a.info/classification/country/JM</uri>
      </binding>
      <binding name="obsValue">
        <literal datatype="http://www.w3.org/2001/XMLSchema#decimal">134313</literal>
      </binding>
    </result>
    <result>
      <binding name="refArea">
        <uri>http://worldbank.270a.info/classification/country/JO</uri>
      </binding>
      <binding name="obsValue">
        <literal datatype="http://www.w3.org/2001/XMLSchema#decimal">348633</literal>
      </binding>
    </result>
    <result>
      <binding name="refArea">
        <uri>http://worldbank.270a.info/classification/country/JP</uri>
      </binding>
      <binding name="obsValue">
        <literal datatype="http://www.w3.org/2001/XMLSchema#decimal">2887567</literal>
      </binding>
    </result>
    <result>
      <binding name="refArea">
        <uri>http://worldbank.270a.info/classification/country/KZ</uri>
      </binding>
      <binding name="obsValue">
        <literal datatype="http://www.w3.org/2001/XMLSchema#decimal">518407</literal>
      </binding>
    </result>
    <result>
      <binding name="refArea">
        <uri>http://worldbank.270a.info/classification/country/KE</uri>
      </binding>
      <binding name="obsValue">
        <literal datatype="http://www.w3.org/2001/XMLSchema#decimal">2551277</literal>
      </binding>
    </result>
    <result>
      <binding name="refArea">
        <uri>http://worldbank.270a.info/classification/country/KG</uri>
      </binding>
      <binding name="obsValue">
        <literal datatype="http://www.w3.org/2001/XMLSchema#decimal">245039</literal>
      </binding>
    </result>
    <result>
      <binding name="refArea">
        <uri>http://worldbank.270a.info/classification/country/KH</uri>
      </binding>
      <binding name="obsValue">
        <literal datatype="http://www.w3.org/2001/XMLSchema#decimal">807603</literal>
      </binding>
    </result>
    <result>
      <binding name="refArea">
        <uri>http://worldbank.270a.info/classification/country/KR</uri>
      </binding>
      <binding name="obsValue">
        <literal datatype="http://www.w3.org/2001/XMLSchema#decimal">1328743</literal>
      </binding>
    </result>
    <result>
      <binding name="refArea">
        <uri>http://worldbank.270a.info/classification/country/KW</uri>
      </binding>
      <binding name="obsValue">
        <literal datatype="http://www.w3.org/2001/XMLSchema#decimal">110511</literal>
      </binding>
    </result>
    <result>
      <binding name="refArea">
        <uri>http://worldbank.270a.info/classification/country/LA</uri>
      </binding>
      <binding name="obsValue">
        <literal datatype="http://www.w3.org/2001/XMLSchema#decimal">353973</literal>
      </binding>
    </result>
    <result>
      <binding name="refArea">
        <uri>http://worldbank.270a.info/classification/country/LB</uri>
      </binding>
      <binding name="obsValue">
        <literal datatype="http://www.w3.org/2001/XMLSchema#decimal">186606</literal>
      </binding>
    </result>
    <result>
      <binding name="refArea">
        <uri>http://worldbank.270a.info/classification/country/LR</uri>
      </binding>
      <binding name="obsValue">
        <literal datatype="http://www.w3.org/2001/XMLSchema#decimal">292877</literal>
      </binding>
    </result>
    <result>
      <binding name="refArea">
        <uri>http://worldbank.270a.info/classification/country/LY</uri>
      </binding>
      <binding name="obsValue">
        <literal datatype="http://www.w3.org/2001/XMLSchema#decimal">301969</literal>
      </binding>
    </result>
    <result>
      <binding name="refArea">
        <uri>http://worldbank.270a.info/classification/country/LC</uri>
      </binding>
      <binding name="obsValue">
        <literal datatype="http://www.w3.org/2001/XMLSchema#decimal">7009</literal>
      </binding>
    </result>
    <result>
      <binding name="refArea">
        <uri>http://worldbank.270a.info/classification/country/LK</uri>
      </binding>
      <binding name="obsValue">
        <literal datatype="http://www.w3.org/2001/XMLSchema#decimal">725096</literal>
      </binding>
    </result>
    <result>
      <binding name="refArea">
        <uri>http://worldbank.270a.info/classification/country/LS</uri>
      </binding>
      <binding name="obsValue">
        <literal datatype="http://www.w3.org/2001/XMLSchema#decimal">130976</literal>
      </binding>
    </result>
    <result>
      <binding name="refArea">
        <uri>http://worldbank.270a.info/classification/country/LT</uri>
      </binding>
      <binding name="obsValue">
        <literal datatype="http://www.w3.org/2001/XMLSchema#decimal">80591</literal>
      </binding>
    </result>
    <result>
      <binding name="refArea">
        <uri>http://worldbank.270a.info/classification/country/LU</uri>
      </binding>
      <binding name="obsValue">
        <literal datatype="http://www.w3.org/2001/XMLSchema#decimal">14568</literal>
      </binding>
    </result>
    <result>
      <binding name="refArea">
        <uri>http://worldbank.270a.info/classification/country/LV</uri>
      </binding>
      <binding name="obsValue">
        <literal datatype="http://www.w3.org/2001/XMLSchema#decimal">46465</literal>
      </binding>
    </result>
    <result>
      <binding name="refArea">
        <uri>http://worldbank.270a.info/classification/country/MO</uri>
      </binding>
      <binding name="obsValue">
        <literal datatype="http://www.w3.org/2001/XMLSchema#decimal">10344</literal>
      </binding>
    </result>
    <result>
      <binding name="refArea">
        <uri>http://worldbank.270a.info/classification/country/MA</uri>
      </binding>
      <binding name="obsValue">
        <literal datatype="http://www.w3.org/2001/XMLSchema#decimal">1452105</literal>
      </binding>
    </result>
    <result>
      <binding name="refArea">
        <uri>http://worldbank.270a.info/classification/country/MD</uri>
      </binding>
      <binding name="obsValue">
        <literal datatype="http://www.w3.org/2001/XMLSchema#decimal">107533</literal>
      </binding>
    </result>
    <result>
      <binding name="refArea">
        <uri>http://worldbank.270a.info/classification/country/MG</uri>
      </binding>
      <binding name="obsValue">
        <literal datatype="http://www.w3.org/2001/XMLSchema#decimal">1398164</literal>
      </binding>
    </result>
    <result>
      <binding name="refArea">
        <uri>http://worldbank.270a.info/classification/country/MV</uri>
      </binding>
      <binding name="obsValue">
        <literal datatype="http://www.w3.org/2001/XMLSchema#decimal">14657</literal>
      </binding>
    </result>
    <result>
      <binding name="refArea">
        <uri>http://worldbank.270a.info/classification/country/MX</uri>
      </binding>
      <binding name="obsValue">
        <literal datatype="http://www.w3.org/2001/XMLSchema#decimal">5134025</literal>
      </binding>
    </result>
    <result>
      <binding name="refArea">
        <uri>http://worldbank.270a.info/classification/country/MK</uri>
      </binding>
      <binding name="obsValue">
        <literal datatype="http://www.w3.org/2001/XMLSchema#decimal">59668</literal>
      </binding>
    </result>
    <result>
      <binding name="refArea">
        <uri>http://worldbank.270a.info/classification/country/ML</uri>
      </binding>
      <binding name="obsValue">
        <literal datatype="http://www.w3.org/2001/XMLSchema#decimal">929516</literal>
      </binding>
    </result>
    <result>
      <binding name="refArea">
        <uri>http://worldbank.270a.info/classification/country/MT</uri>
      </binding>
      <binding name="obsValue">
        <literal datatype="http://www.w3.org/2001/XMLSchema#decimal">10771</literal>
      </binding>
    </result>
    <result>
      <binding name="refArea">
        <uri>http://worldbank.270a.info/classification/country/MM</uri>
      </binding>
      <binding name="obsValue">
        <literal datatype="http://www.w3.org/2001/XMLSchema#decimal">2061982</literal>
      </binding>
    </result>
    <result>
      <binding name="refArea">
        <uri>http://worldbank.270a.info/classification/country/MN</uri>
      </binding>
      <binding name="obsValue">
        <literal datatype="http://www.w3.org/2001/XMLSchema#decimal">110463</literal>
      </binding>
    </result>
    <result>
      <binding name="refArea">
        <uri>http://worldbank.270a.info/classification/country/MZ</uri>
      </binding>
      <binding name="obsValue">
        <literal datatype="http://www.w3.org/2001/XMLSchema#decimal">1539428</literal>
      </binding>
    </result>
    <result>
      <binding name="refArea">
        <uri>http://worldbank.270a.info/classification/country/MR</uri>
      </binding>
      <binding name="obsValue">
        <literal datatype="http://www.w3.org/2001/XMLSchema#decimal">199489</literal>
      </binding>
    </result>
    <result>
      <binding name="refArea">
        <uri>http://worldbank.270a.info/classification/country/MU</uri>
      </binding>
      <binding name="obsValue">
        <literal datatype="http://www.w3.org/2001/XMLSchema#decimal">47855</literal>
      </binding>
    </result>
    <result>
      <binding name="refArea">
        <uri>http://worldbank.270a.info/classification/country/MW</uri>
      </binding>
      <binding name="obsValue">
        <literal datatype="http://www.w3.org/2001/XMLSchema#decimal">1070208</literal>
      </binding>
    </result>
    <result>
      <binding name="refArea">
        <uri>http://worldbank.270a.info/classification/country/MY</uri>
      </binding>
      <binding name="obsValue">
        <literal datatype="http://www.w3.org/2001/XMLSchema#decimal">1318012</literal>
      </binding>
    </result>
    <result>
      <binding name="refArea">
        <uri>http://worldbank.270a.info/classification/country/NA</uri>
      </binding>
      <binding name="obsValue">
        <literal datatype="http://www.w3.org/2001/XMLSchema#decimal">125247</literal>
      </binding>
    </result>
    <result>
      <binding name="refArea">
        <uri>http://worldbank.270a.info/classification/country/NE</uri>
      </binding>
      <binding name="obsValue">
        <literal datatype="http://www.w3.org/2001/XMLSchema#decimal">1068818</literal>
      </binding>
    </result>
    <result>
      <binding name="refArea">
        <uri>http://worldbank.270a.info/classification/country/NG</uri>
      </binding>
      <binding name="obsValue">
        <literal datatype="http://www.w3.org/2001/XMLSchema#decimal">10206824</literal>
      </binding>
    </result>
    <result>
      <binding name="refArea">
        <uri>http://worldbank.270a.info/classification/country/NI</uri>
      </binding>
      <binding name="obsValue">
        <literal datatype="http://www.w3.org/2001/XMLSchema#decimal">321673</literal>
      </binding>
    </result>
    <result>
      <binding name="refArea">
        <uri>http://worldbank.270a.info/classification/country/NL</uri>
      </binding>
      <binding name="obsValue">
        <literal datatype="http://www.w3.org/2001/XMLSchema#decimal">490559</literal>
      </binding>
    </result>
    <result>
      <binding name="refArea">
        <uri>http://worldbank.270a.info/classification/country/NO</uri>
      </binding>
      <binding name="obsValue">
        <literal datatype="http://www.w3.org/2001/XMLSchema#decimal">149979</literal>
      </binding>
    </result>
    <result>
      <binding name="refArea">
        <uri>http://worldbank.270a.info/classification/country/NP</uri>
      </binding>
      <binding name="obsValue">
        <literal datatype="http://www.w3.org/2001/XMLSchema#decimal">1717684</literal>
      </binding>
    </result>
    <result>
      <binding name="refArea">
        <uri>http://worldbank.270a.info/classification/country/NZ</uri>
      </binding>
      <binding name="obsValue">
        <literal datatype="http://www.w3.org/2001/XMLSchema#decimal">141485</literal>
      </binding>
    </result>
    <result>
      <binding name="refArea">
        <uri>http://worldbank.270a.info/classification/country/OM</uri>
      </binding>
      <binding name="obsValue">
        <literal datatype="http://www.w3.org/2001/XMLSchema#decimal">136604</literal>
      </binding>
    </result>
    <result>
      <binding name="refArea">
        <uri>http://worldbank.270a.info/classification/country/PK</uri>
      </binding>
      <binding name="obsValue">
        <literal datatype="http://www.w3.org/2001/XMLSchema#decimal">9129929</literal>
      </binding>
    </result>
    <result>
      <binding name="refArea">
        <uri>http://worldbank.270a.info/classification/country/PA</uri>
      </binding>
      <binding name="obsValue">
        <literal datatype="http://www.w3.org/2001/XMLSchema#decimal">164362</literal>
      </binding>
    </result>
    <result>
      <binding name="refArea">
        <uri>http://worldbank.270a.info/classification/country/PE</uri>
      </binding>
      <binding name="obsValue">
        <literal datatype="http://www.w3.org/2001/XMLSchema#decimal">1337481</literal>
      </binding>
    </result>
    <result>
      <binding name="refArea">
        <uri>http://worldbank.270a.info/classification/country/PH</uri>
      </binding>
      <binding name="obsValue">
        <literal datatype="http://www.w3.org/2001/XMLSchema#decimal">5052933</literal>
      </binding>
    </result>
    <result>
      <binding name="refArea">
        <uri>http://worldbank.270a.info/classification/country/PG</uri>
      </binding>
      <binding name="obsValue">
        <literal datatype="http://www.w3.org/2001/XMLSchema#decimal">418110</literal>
      </binding>
    </result>
    <result>
      <binding name="refArea">
        <uri>http://worldbank.270a.info/classification/country/PL</uri>
      </binding>
      <binding name="obsValue">
        <literal datatype="http://www.w3.org/2001/XMLSchema#decimal">904636</literal>
      </binding>
    </result>
    <result>
      <binding name="refArea">
        <uri>http://worldbank.270a.info/classification/country/KP</uri>
      </binding>
      <binding name="obsValue">
        <literal datatype="http://www.w3.org/2001/XMLSchema#decimal">895906</literal>
      </binding>
    </result>
    <result>
      <binding name="refArea">
        <uri>http://worldbank.270a.info/classification/country/PT</uri>
      </binding>
      <binding name="obsValue">
        <literal datatype="http://www.w3.org/2001/XMLSchema#decimal">271367</literal>
      </binding>
    </result>
    <result>
      <binding name="refArea">
        <uri>http://worldbank.270a.info/classification/country/PY</uri>
      </binding>
      <binding name="obsValue">
        <literal datatype="http://www.w3.org/2001/XMLSchema#decimal">348521</literal>
      </binding>
    </result>
    <result>
      <binding name="refArea">
        <uri>http://worldbank.270a.info/classification/country/QA</uri>
      </binding>
      <binding name="obsValue">
        <literal datatype="http://www.w3.org/2001/XMLSchema#decimal">29261</literal>
      </binding>
    </result>
    <result>
      <binding name="refArea">
        <uri>http://worldbank.270a.info/classification/country/RO</uri>
      </binding>
      <binding name="obsValue">
        <literal datatype="http://www.w3.org/2001/XMLSchema#decimal">523263</literal>
      </binding>
    </result>
    <result>
      <binding name="refArea">
        <uri>http://worldbank.270a.info/classification/country/RU</uri>
      </binding>
      <binding name="obsValue">
        <literal datatype="http://www.w3.org/2001/XMLSchema#decimal">3221995</literal>
      </binding>
    </result>
    <result>
      <binding name="refArea">
        <uri>http://worldbank.270a.info/classification/country/RW</uri>
      </binding>
      <binding name="obsValue">
        <literal datatype="http://www.w3.org/2001/XMLSchema#decimal">639388</literal>
      </binding>
    </result>
    <result>
      <binding name="refArea">
        <uri>http://worldbank.270a.info/classification/country/SA</uri>
      </binding>
      <binding name="obsValue">
        <literal datatype="http://www.w3.org/2001/XMLSchema#decimal">1347968</literal>
      </binding>
    </result>
    <result>
      <binding name="refArea">
        <uri>http://worldbank.270a.info/classification/country/SD</uri>
      </binding>
      <binding name="obsValue">
        <literal datatype="http://www.w3.org/2001/XMLSchema#decimal">2507353</literal>
      </binding>
    </result>
    <result>
      <binding name="refArea">
        <uri>http://worldbank.270a.info/classification/country/SN</uri>
      </binding>
      <binding name="obsValue">
        <literal datatype="http://www.w3.org/2001/XMLSchema#decimal">834980</literal>
      </binding>
    </result>
    <result>
      <binding name="refArea">
        <uri>http://worldbank.270a.info/classification/country/SG</uri>
      </binding>
      <binding name="obsValue">
        <literal datatype="http://www.w3.org/2001/XMLSchema#decimal">133327</literal>
      </binding>
    </result>
    <result>
      <binding name="refArea">
        <uri>http://worldbank.270a.info/classification/country/SB</uri>
      </binding>
      <binding name="obsValue">
        <literal datatype="http://www.w3.org/2001/XMLSchema#decimal">31304</literal>
      </binding>
    </result>
    <result>
      <binding name="refArea">
        <uri>http://worldbank.270a.info/classification/country/SL</uri>
      </binding>
      <binding name="obsValue">
        <literal datatype="http://www.w3.org/2001/XMLSchema#decimal">387403</literal>
      </binding>
    </result>
    <result>
      <binding name="refArea">
        <uri>http://worldbank.270a.info/classification/country/SV</uri>
      </binding>
      <binding name="obsValue">
        <literal datatype="http://www.w3.org/2001/XMLSchema#decimal">369585</literal>
      </binding>
    </result>
    <result>
      <binding name="refArea">
        <uri>http://worldbank.270a.info/classification/country/SO</uri>
      </binding>
      <binding name="obsValue">
        <literal datatype="http://www.w3.org/2001/XMLSchema#decimal">625581</literal>
      </binding>
    </result>
    <result>
      <binding name="refArea">
        <uri>http://worldbank.270a.info/classification/country/ST</uri>
      </binding>
      <binding name="obsValue">
        <literal datatype="http://www.w3.org/2001/XMLSchema#decimal">10585</literal>
      </binding>
    </result>
    <result>
      <binding name="refArea">
        <uri>http://worldbank.270a.info/classification/country/SR</uri>
      </binding>
      <binding name="obsValue">
        <literal datatype="http://www.w3.org/2001/XMLSchema#decimal">21046</literal>
      </binding>
    </result>
    <result>
      <binding name="refArea">
        <uri>http://worldbank.270a.info/classification/country/SK</uri>
      </binding>
      <binding name="obsValue">
        <literal datatype="http://www.w3.org/2001/XMLSchema#decimal">132276</literal>
      </binding>
    </result>
    <result>
      <binding name="refArea">
        <uri>http://worldbank.270a.info/classification/country/SI</uri>
      </binding>
      <binding name="obsValue">
        <literal datatype="http://www.w3.org/2001/XMLSchema#decimal">43667</literal>
      </binding>
    </result>
    <result>
      <binding name="refArea">
        <uri>http://worldbank.270a.info/classification/country/SE</uri>
      </binding>
      <binding name="obsValue">
        <literal datatype="http://www.w3.org/2001/XMLSchema#decimal">240839</literal>
      </binding>
    </result>
    <result>
      <binding name="refArea">
        <uri>http://worldbank.270a.info/classification/country/SZ</uri>
      </binding>
      <binding name="obsValue">
        <literal datatype="http://www.w3.org/2001/XMLSchema#decimal">70399</literal>
      </binding>
    </result>
    <result>
      <binding name="refArea">
        <uri>http://worldbank.270a.info/classification/country/SY</uri>
      </binding>
      <binding name="obsValue">
        <literal datatype="http://www.w3.org/2001/XMLSchema#decimal">1143098</literal>
      </binding>
    </result>
    <result>
      <binding name="refArea">
        <uri>http://worldbank.270a.info/classification/country/TD</uri>
      </binding>
      <binding name="obsValue">
        <literal datatype="http://www.w3.org/2001/XMLSchema#decimal">790021</literal>
      </binding>
    </result>
    <result>
      <binding name="refArea">
        <uri>http://worldbank.270a.info/classification/country/TG</uri>
      </binding>
      <binding name="obsValue">
        <literal datatype="http://www.w3.org/2001/XMLSchema#decimal">464491</literal>
      </binding>
    </result>
    <result>
      <binding name="refArea">
        <uri>http://worldbank.270a.info/classification/country/TH</uri>
      </binding>
      <binding name="obsValue">
        <literal datatype="http://www.w3.org/2001/XMLSchema#decimal">2155659</literal>
      </binding>
    </result>
    <result>
      <binding name="refArea">
        <uri>http://worldbank.270a.info/classification/country/TJ</uri>
      </binding>
      <binding name="obsValue">
        <literal datatype="http://www.w3.org/2001/XMLSchema#decimal">410997</literal>
      </binding>
    </result>
    <result>
      <binding name="refArea">
        <uri>http://worldbank.270a.info/classification/country/TM</uri>
      </binding>
      <binding name="obsValue">
        <literal datatype="http://www.w3.org/2001/XMLSchema#decimal">232787</literal>
      </binding>
    </result>
    <result>
      <binding name="refArea">
        <uri>http://worldbank.270a.info/classification/country/TL</uri>
      </binding>
      <binding name="obsValue">
        <literal datatype="http://www.w3.org/2001/XMLSchema#decimal">80899</literal>
      </binding>
    </result>
    <result>
      <binding name="refArea">
        <uri>http://worldbank.270a.info/classification/country/TO</uri>
      </binding>
      <binding name="obsValue">
        <literal datatype="http://www.w3.org/2001/XMLSchema#decimal">5691</literal>
      </binding>
    </result>
    <result>
      <binding name="refArea">
        <uri>http://worldbank.270a.info/classification/country/TT</uri>
      </binding>
      <binding name="obsValue">
        <literal datatype="http://www.w3.org/2001/XMLSchema#decimal">44389</literal>
      </binding>
    </result>
    <result>
      <binding name="refArea">
        <uri>http://worldbank.270a.info/classification/country/TN</uri>
      </binding>
      <binding name="obsValue">
        <literal datatype="http://www.w3.org/2001/XMLSchema#decimal">393701</literal>
      </binding>
    </result>
    <result>
      <binding name="refArea">
        <uri>http://worldbank.270a.info/classification/country/TR</uri>
      </binding>
      <binding name="obsValue">
        <literal datatype="http://www.w3.org/2001/XMLSchema#decimal">3342317</literal>
      </binding>
    </result>
    <result>
      <binding name="refArea">
        <uri>http://worldbank.270a.info/classification/country/TZ</uri>
      </binding>
      <binding name="obsValue">
        <literal datatype="http://www.w3.org/2001/XMLSchema#decimal">2898210</literal>
      </binding>
    </result>
    <result>
      <binding name="refArea">
        <uri>http://worldbank.270a.info/classification/country/UG</uri>
      </binding>
      <binding name="obsValue">
        <literal datatype="http://www.w3.org/2001/XMLSchema#decimal">2391486</literal>
      </binding>
    </result>
    <result>
      <binding name="refArea">
        <uri>http://worldbank.270a.info/classification/country/UA</uri>
      </binding>
      <binding name="obsValue">
        <literal datatype="http://www.w3.org/2001/XMLSchema#decimal">969736</literal>
      </binding>
    </result>
    <result>
      <binding name="refArea">
        <uri>http://worldbank.270a.info/classification/country/UY</uri>
      </binding>
      <binding name="obsValue">
        <literal datatype="http://www.w3.org/2001/XMLSchema#decimal">125580</literal>
      </binding>
    </result>
    <result>
      <binding name="refArea">
        <uri>http://worldbank.270a.info/classification/country/US</uri>
      </binding>
      <binding name="obsValue">
        <literal datatype="http://www.w3.org/2001/XMLSchema#decimal">10361562</literal>
      </binding>
    </result>
    <result>
      <binding name="refArea">
        <uri>http://worldbank.270a.info/classification/country/UZ</uri>
      </binding>
      <binding name="obsValue">
        <literal datatype="http://www.w3.org/2001/XMLSchema#decimal">1348172</literal>
      </binding>
    </result>
    <result>
      <binding name="refArea">
        <uri>http://worldbank.270a.info/classification/country/VC</uri>
      </binding>
      <binding name="obsValue">
        <literal datatype="http://www.w3.org/2001/XMLSchema#decimal">5225</literal>
      </binding>
    </result>
    <result>
      <binding name="refArea">
        <uri>http://worldbank.270a.info/classification/country/VE</uri>
      </binding>
      <binding name="obsValue">
        <literal datatype="http://www.w3.org/2001/XMLSchema#decimal">1370983</literal>
      </binding>
    </result>
    <result>
      <binding name="refArea">
        <uri>http://worldbank.270a.info/classification/country/VN</uri>
      </binding>
      <binding name="obsValue">
        <literal datatype="http://www.w3.org/2001/XMLSchema#decimal">3850924</literal>
      </binding>
    </result>
    <result>
      <binding name="refArea">
        <uri>http://worldbank.270a.info/classification/country/VU</uri>
      </binding>
      <binding name="obsValue">
        <literal datatype="http://www.w3.org/2001/XMLSchema#decimal">14179</literal>
      </binding>
    </result>
    <result>
      <binding name="refArea">
        <uri>http://worldbank.270a.info/classification/country/PS</uri>
      </binding>
      <binding name="obsValue">
        <literal datatype="http://www.w3.org/2001/XMLSchema#decimal">300942</literal>
      </binding>
    </result>
    <result>
      <binding name="refArea">
        <uri>http://worldbank.270a.info/classification/country/WS</uri>
      </binding>
      <binding name="obsValue">
        <literal datatype="http://www.w3.org/2001/XMLSchema#decimal">12198</literal>
      </binding>
    </result>
    <result>
      <binding name="refArea">
        <uri>http://worldbank.270a.info/classification/country/YE</uri>
      </binding>
      <binding name="obsValue">
        <literal datatype="http://www.w3.org/2001/XMLSchema#decimal">1600634</literal>
      </binding>
    </result>
    <result>
      <binding name="refArea">
        <uri>http://worldbank.270a.info/classification/country/ZA</uri>
      </binding>
      <binding name="obsValue">
        <literal datatype="http://www.w3.org/2001/XMLSchema#decimal">2538203</literal>
      </binding>
    </result>
    <result>
      <binding name="refArea">
        <uri>http://worldbank.270a.info/classification/country/CD</uri>
      </binding>
      <binding name="obsValue">
        <literal datatype="http://www.w3.org/2001/XMLSchema#decimal">4631130</literal>
      </binding>
    </result>
    <result>
      <binding name="refArea">
        <uri>http://worldbank.270a.info/classification/country/ZM</uri>
      </binding>
      <binding name="obsValue">
        <literal datatype="http://www.w3.org/2001/XMLSchema#decimal">874633</literal>
      </binding>
    </result>
    <result>
      <binding name="refArea">
        <uri>http://worldbank.270a.info/classification/country/ZW</uri>
      </binding>
      <binding name="obsValue">
        <literal datatype="http://www.w3.org/2001/XMLSchema#decimal">825716</literal>
      </binding>
    </result>
  </results>
</sparql>
