<?xml version="1.0"?>
<sparql xmlns="http://www.w3.org/2005/sparql-results#">
  <head>
    <variable name="refArea"/>
    <variable name="obsValue"/>
  </head>
  <results>
    <result>
      <binding name="refArea">
        <uri>http://worldbank.270a.info/classification/country/AM</uri>
      </binding>
      <binding name="obsValue">
        <literal datatype="http://www.w3.org/2001/XMLSchema#decimal">92876</literal>
      </binding>
    </result>
    <result>
      <binding name="refArea">
        <uri>http://worldbank.270a.info/classification/country/AG</uri>
      </binding>
      <binding name="obsValue">
        <literal datatype="http://www.w3.org/2001/XMLSchema#decimal">3179</literal>
      </binding>
    </result>
    <result>
      <binding name="refArea">
        <uri>http://worldbank.270a.info/classification/country/AU</uri>
      </binding>
      <binding name="obsValue">
        <literal datatype="http://www.w3.org/2001/XMLSchema#decimal">297480</literal>
      </binding>
    </result>
    <result>
      <binding name="refArea">
        <uri>http://worldbank.270a.info/classification/country/AT</uri>
      </binding>
      <binding name="obsValue">
        <literal datatype="http://www.w3.org/2001/XMLSchema#decimal">201545</literal>
      </binding>
    </result>
    <result>
      <binding name="refArea">
        <uri>http://worldbank.270a.info/classification/country/BE</uri>
      </binding>
      <binding name="obsValue">
        <literal datatype="http://www.w3.org/2001/XMLSchema#decimal">133222</literal>
      </binding>
    </result>
    <result>
      <binding name="refArea">
        <uri>http://worldbank.270a.info/classification/country/BJ</uri>
      </binding>
      <binding name="obsValue">
        <literal datatype="http://www.w3.org/2001/XMLSchema#decimal">398251</literal>
      </binding>
    </result>
    <result>
      <binding name="refArea">
        <uri>http://worldbank.270a.info/classification/country/BF</uri>
      </binding>
      <binding name="obsValue">
        <literal datatype="http://www.w3.org/2001/XMLSchema#decimal">333206</literal>
      </binding>
    </result>
    <result>
      <binding name="refArea">
        <uri>http://worldbank.270a.info/classification/country/BD</uri>
      </binding>
      <binding name="obsValue">
        <literal datatype="http://www.w3.org/2001/XMLSchema#decimal">9625862</literal>
      </binding>
    </result>
    <result>
      <binding name="refArea">
        <uri>http://worldbank.270a.info/classification/country/BG</uri>
      </binding>
      <binding name="obsValue">
        <literal datatype="http://www.w3.org/2001/XMLSchema#decimal">146854</literal>
      </binding>
    </result>
    <result>
      <binding name="refArea">
        <uri>http://worldbank.270a.info/classification/country/BH</uri>
      </binding>
      <binding name="obsValue">
        <literal datatype="http://www.w3.org/2001/XMLSchema#decimal">31615</literal>
      </binding>
    </result>
    <result>
      <binding name="refArea">
        <uri>http://worldbank.270a.info/classification/country/BS</uri>
      </binding>
      <binding name="obsValue">
        <literal datatype="http://www.w3.org/2001/XMLSchema#decimal">6370</literal>
      </binding>
    </result>
    <result>
      <binding name="refArea">
        <uri>http://worldbank.270a.info/classification/country/BY</uri>
      </binding>
      <binding name="obsValue">
        <literal datatype="http://www.w3.org/2001/XMLSchema#decimal">321026</literal>
      </binding>
    </result>
    <result>
      <binding name="refArea">
        <uri>http://worldbank.270a.info/classification/country/BZ</uri>
      </binding>
      <binding name="obsValue">
        <literal datatype="http://www.w3.org/2001/XMLSchema#decimal">13418</literal>
      </binding>
    </result>
    <result>
      <binding name="refArea">
        <uri>http://worldbank.270a.info/classification/country/BO</uri>
      </binding>
      <binding name="obsValue">
        <literal datatype="http://www.w3.org/2001/XMLSchema#decimal">664841</literal>
      </binding>
    </result>
    <result>
      <binding name="refArea">
        <uri>http://worldbank.270a.info/classification/country/BB</uri>
      </binding>
      <binding name="obsValue">
        <literal datatype="http://www.w3.org/2001/XMLSchema#decimal">7814</literal>
      </binding>
    </result>
    <result>
      <binding name="refArea">
        <uri>http://worldbank.270a.info/classification/country/BN</uri>
      </binding>
      <binding name="obsValue">
        <literal datatype="http://www.w3.org/2001/XMLSchema#decimal">7048</literal>
      </binding>
    </result>
    <result>
      <binding name="refArea">
        <uri>http://worldbank.270a.info/classification/country/BT</uri>
      </binding>
      <binding name="obsValue">
        <literal datatype="http://www.w3.org/2001/XMLSchema#decimal">46324</literal>
      </binding>
    </result>
    <result>
      <binding name="refArea">
        <uri>http://worldbank.270a.info/classification/country/BW</uri>
      </binding>
      <binding name="obsValue">
        <literal datatype="http://www.w3.org/2001/XMLSchema#decimal">88802</literal>
      </binding>
    </result>
    <result>
      <binding name="refArea">
        <uri>http://worldbank.270a.info/classification/country/CA</uri>
      </binding>
      <binding name="obsValue">
        <literal datatype="http://www.w3.org/2001/XMLSchema#decimal">908905</literal>
      </binding>
    </result>
    <result>
      <binding name="refArea">
        <uri>http://worldbank.270a.info/classification/country/CH</uri>
      </binding>
      <binding name="obsValue">
        <literal datatype="http://www.w3.org/2001/XMLSchema#decimal">93748</literal>
      </binding>
    </result>
    <result>
      <binding name="refArea">
        <uri>http://worldbank.270a.info/classification/country/CI</uri>
      </binding>
      <binding name="obsValue">
        <literal datatype="http://www.w3.org/2001/XMLSchema#decimal">781977</literal>
      </binding>
    </result>
    <result>
      <binding name="refArea">
        <uri>http://worldbank.270a.info/classification/country/CM</uri>
      </binding>
      <binding name="obsValue">
        <literal datatype="http://www.w3.org/2001/XMLSchema#decimal">891439</literal>
      </binding>
    </result>
    <result>
      <binding name="refArea">
        <uri>http://worldbank.270a.info/classification/country/CG</uri>
      </binding>
      <binding name="obsValue">
        <literal datatype="http://www.w3.org/2001/XMLSchema#decimal">159064</literal>
      </binding>
    </result>
    <result>
      <binding name="refArea">
        <uri>http://worldbank.270a.info/classification/country/KM</uri>
      </binding>
      <binding name="obsValue">
        <literal datatype="http://www.w3.org/2001/XMLSchema#decimal">25314</literal>
      </binding>
    </result>
    <result>
      <binding name="refArea">
        <uri>http://worldbank.270a.info/classification/country/CV</uri>
      </binding>
      <binding name="obsValue">
        <literal datatype="http://www.w3.org/2001/XMLSchema#decimal">34814</literal>
      </binding>
    </result>
    <result>
      <binding name="refArea">
        <uri>http://worldbank.270a.info/classification/country/CU</uri>
      </binding>
      <binding name="obsValue">
        <literal datatype="http://www.w3.org/2001/XMLSchema#decimal">301126</literal>
      </binding>
    </result>
    <result>
      <binding name="refArea">
        <uri>http://worldbank.270a.info/classification/country/KY</uri>
      </binding>
      <binding name="obsValue">
        <literal datatype="http://www.w3.org/2001/XMLSchema#decimal">1471</literal>
      </binding>
    </result>
    <result>
      <binding name="refArea">
        <uri>http://worldbank.270a.info/classification/country/CZ</uri>
      </binding>
      <binding name="obsValue">
        <literal datatype="http://www.w3.org/2001/XMLSchema#decimal">248783</literal>
      </binding>
    </result>
    <result>
      <binding name="refArea">
        <uri>http://worldbank.270a.info/classification/country/DE</uri>
      </binding>
      <binding name="obsValue">
        <literal datatype="http://www.w3.org/2001/XMLSchema#decimal">2682888</literal>
      </binding>
    </result>
    <result>
      <binding name="refArea">
        <uri>http://worldbank.270a.info/classification/country/DM</uri>
      </binding>
      <binding name="obsValue">
        <literal datatype="http://www.w3.org/2001/XMLSchema#decimal">2904</literal>
      </binding>
    </result>
    <result>
      <binding name="refArea">
        <uri>http://worldbank.270a.info/classification/country/DK</uri>
      </binding>
      <binding name="obsValue">
        <literal datatype="http://www.w3.org/2001/XMLSchema#decimal">142477</literal>
      </binding>
    </result>
    <result>
      <binding name="refArea">
        <uri>http://worldbank.270a.info/classification/country/EG</uri>
      </binding>
      <binding name="obsValue">
        <literal datatype="http://www.w3.org/2001/XMLSchema#decimal">2951590</literal>
      </binding>
    </result>
    <result>
      <binding name="refArea">
        <uri>http://worldbank.270a.info/classification/country/ER</uri>
      </binding>
      <binding name="obsValue">
        <literal datatype="http://www.w3.org/2001/XMLSchema#decimal">245985</literal>
      </binding>
    </result>
    <result>
      <binding name="refArea">
        <uri>http://worldbank.270a.info/classification/country/ES</uri>
      </binding>
      <binding name="obsValue">
        <literal datatype="http://www.w3.org/2001/XMLSchema#decimal">1288659</literal>
      </binding>
    </result>
    <result>
      <binding name="refArea">
        <uri>http://worldbank.270a.info/classification/country/EE</uri>
      </binding>
      <binding name="obsValue">
        <literal datatype="http://www.w3.org/2001/XMLSchema#decimal">28389</literal>
      </binding>
    </result>
    <result>
      <binding name="refArea">
        <uri>http://worldbank.270a.info/classification/country/FI</uri>
      </binding>
      <binding name="obsValue">
        <literal datatype="http://www.w3.org/2001/XMLSchema#decimal">205379</literal>
      </binding>
    </result>
    <result>
      <binding name="refArea">
        <uri>http://worldbank.270a.info/classification/country/FR</uri>
      </binding>
      <binding name="obsValue">
        <literal datatype="http://www.w3.org/2001/XMLSchema#decimal">1548416</literal>
      </binding>
    </result>
    <result>
      <binding name="refArea">
        <uri>http://worldbank.270a.info/classification/country/FM</uri>
      </binding>
      <binding name="obsValue">
        <literal datatype="http://www.w3.org/2001/XMLSchema#decimal">4985</literal>
      </binding>
    </result>
    <result>
      <binding name="refArea">
        <uri>http://worldbank.270a.info/classification/country/GA</uri>
      </binding>
      <binding name="obsValue">
        <literal datatype="http://www.w3.org/2001/XMLSchema#decimal">65461</literal>
      </binding>
    </result>
    <result>
      <binding name="refArea">
        <uri>http://worldbank.270a.info/classification/country/GE</uri>
      </binding>
      <binding name="obsValue">
        <literal datatype="http://www.w3.org/2001/XMLSchema#decimal">62889</literal>
      </binding>
    </result>
    <result>
      <binding name="refArea">
        <uri>http://worldbank.270a.info/classification/country/GM</uri>
      </binding>
      <binding name="obsValue">
        <literal datatype="http://www.w3.org/2001/XMLSchema#decimal">69594</literal>
      </binding>
    </result>
    <result>
      <binding name="refArea">
        <uri>http://worldbank.270a.info/classification/country/GR</uri>
      </binding>
      <binding name="obsValue">
        <literal datatype="http://www.w3.org/2001/XMLSchema#decimal">218875</literal>
      </binding>
    </result>
    <result>
      <binding name="refArea">
        <uri>http://worldbank.270a.info/classification/country/GD</uri>
      </binding>
      <binding name="obsValue">
        <literal datatype="http://www.w3.org/2001/XMLSchema#decimal">4126</literal>
      </binding>
    </result>
    <result>
      <binding name="refArea">
        <uri>http://worldbank.270a.info/classification/country/GY</uri>
      </binding>
      <binding name="obsValue">
        <literal datatype="http://www.w3.org/2001/XMLSchema#decimal">31109</literal>
      </binding>
    </result>
    <result>
      <binding name="refArea">
        <uri>http://worldbank.270a.info/classification/country/HT</uri>
      </binding>
      <binding name="obsValue">
        <literal datatype="http://www.w3.org/2001/XMLSchema#decimal">823632</literal>
      </binding>
    </result>
    <result>
      <binding name="refArea">
        <uri>http://worldbank.270a.info/classification/country/HU</uri>
      </binding>
      <binding name="obsValue">
        <literal datatype="http://www.w3.org/2001/XMLSchema#decimal">354661</literal>
      </binding>
    </result>
    <result>
      <binding name="refArea">
        <uri>http://worldbank.270a.info/classification/country/IE</uri>
      </binding>
      <binding name="obsValue">
        <literal datatype="http://www.w3.org/2001/XMLSchema#decimal">112074</literal>
      </binding>
    </result>
    <result>
      <binding name="refArea">
        <uri>http://worldbank.270a.info/classification/country/IR</uri>
      </binding>
      <binding name="obsValue">
        <literal datatype="http://www.w3.org/2001/XMLSchema#decimal">2630343</literal>
      </binding>
    </result>
    <result>
      <binding name="refArea">
        <uri>http://worldbank.270a.info/classification/country/IQ</uri>
      </binding>
      <binding name="obsValue">
        <literal datatype="http://www.w3.org/2001/XMLSchema#decimal">1334062</literal>
      </binding>
    </result>
    <result>
      <binding name="refArea">
        <uri>http://worldbank.270a.info/classification/country/IS</uri>
      </binding>
      <binding name="obsValue">
        <literal datatype="http://www.w3.org/2001/XMLSchema#decimal">9399</literal>
      </binding>
    </result>
    <result>
      <binding name="refArea">
        <uri>http://worldbank.270a.info/classification/country/IT</uri>
      </binding>
      <binding name="obsValue">
        <literal datatype="http://www.w3.org/2001/XMLSchema#decimal">606929</literal>
      </binding>
    </result>
    <result>
      <binding name="refArea">
        <uri>http://worldbank.270a.info/classification/country/JM</uri>
      </binding>
      <binding name="obsValue">
        <literal datatype="http://www.w3.org/2001/XMLSchema#decimal">109144</literal>
      </binding>
    </result>
    <result>
      <binding name="refArea">
        <uri>http://worldbank.270a.info/classification/country/JP</uri>
      </binding>
      <binding name="obsValue">
        <literal datatype="http://www.w3.org/2001/XMLSchema#decimal">1193679</literal>
      </binding>
    </result>
    <result>
      <binding name="refArea">
        <uri>http://worldbank.270a.info/classification/country/KZ</uri>
      </binding>
      <binding name="obsValue">
        <literal datatype="http://www.w3.org/2001/XMLSchema#decimal">1033195</literal>
      </binding>
    </result>
    <result>
      <binding name="refArea">
        <uri>http://worldbank.270a.info/classification/country/KE</uri>
      </binding>
      <binding name="obsValue">
        <literal datatype="http://www.w3.org/2001/XMLSchema#decimal">1745109</literal>
      </binding>
    </result>
    <result>
      <binding name="refArea">
        <uri>http://worldbank.270a.info/classification/country/KG</uri>
      </binding>
      <binding name="obsValue">
        <literal datatype="http://www.w3.org/2001/XMLSchema#decimal">220299</literal>
      </binding>
    </result>
    <result>
      <binding name="refArea">
        <uri>http://worldbank.270a.info/classification/country/KH</uri>
      </binding>
      <binding name="obsValue">
        <literal datatype="http://www.w3.org/2001/XMLSchema#decimal">1007774</literal>
      </binding>
    </result>
    <result>
      <binding name="refArea">
        <uri>http://worldbank.270a.info/classification/country/KI</uri>
      </binding>
      <binding name="obsValue">
        <literal datatype="http://www.w3.org/2001/XMLSchema#decimal">2268</literal>
      </binding>
    </result>
    <result>
      <binding name="refArea">
        <uri>http://worldbank.270a.info/classification/country/KN</uri>
      </binding>
      <binding name="obsValue">
        <literal datatype="http://www.w3.org/2001/XMLSchema#decimal">1728</literal>
      </binding>
    </result>
    <result>
      <binding name="refArea">
        <uri>http://worldbank.270a.info/classification/country/LA</uri>
      </binding>
      <binding name="obsValue">
        <literal datatype="http://www.w3.org/2001/XMLSchema#decimal">322612</literal>
      </binding>
    </result>
    <result>
      <binding name="refArea">
        <uri>http://worldbank.270a.info/classification/country/LR</uri>
      </binding>
      <binding name="obsValue">
        <literal datatype="http://www.w3.org/2001/XMLSchema#decimal">237000</literal>
      </binding>
    </result>
    <result>
      <binding name="refArea">
        <uri>http://worldbank.270a.info/classification/country/LY</uri>
      </binding>
      <binding name="obsValue">
        <literal datatype="http://www.w3.org/2001/XMLSchema#decimal">334620</literal>
      </binding>
    </result>
    <result>
      <binding name="refArea">
        <uri>http://worldbank.270a.info/classification/country/LC</uri>
      </binding>
      <binding name="obsValue">
        <literal datatype="http://www.w3.org/2001/XMLSchema#decimal">6796</literal>
      </binding>
    </result>
    <result>
      <binding name="refArea">
        <uri>http://worldbank.270a.info/classification/country/LI</uri>
      </binding>
      <binding name="obsValue">
        <literal datatype="http://www.w3.org/2001/XMLSchema#decimal">875</literal>
      </binding>
    </result>
    <result>
      <binding name="refArea">
        <uri>http://worldbank.270a.info/classification/country/LS</uri>
      </binding>
      <binding name="obsValue">
        <literal datatype="http://www.w3.org/2001/XMLSchema#decimal">49252</literal>
      </binding>
    </result>
    <result>
      <binding name="refArea">
        <uri>http://worldbank.270a.info/classification/country/LT</uri>
      </binding>
      <binding name="obsValue">
        <literal datatype="http://www.w3.org/2001/XMLSchema#decimal">42302</literal>
      </binding>
    </result>
    <result>
      <binding name="refArea">
        <uri>http://worldbank.270a.info/classification/country/LU</uri>
      </binding>
      <binding name="obsValue">
        <literal datatype="http://www.w3.org/2001/XMLSchema#decimal">19403</literal>
      </binding>
    </result>
    <result>
      <binding name="refArea">
        <uri>http://worldbank.270a.info/classification/country/LV</uri>
      </binding>
      <binding name="obsValue">
        <literal datatype="http://www.w3.org/2001/XMLSchema#decimal">52871</literal>
      </binding>
    </result>
    <result>
      <binding name="refArea">
        <uri>http://worldbank.270a.info/classification/country/MG</uri>
      </binding>
      <binding name="obsValue">
        <literal datatype="http://www.w3.org/2001/XMLSchema#decimal">931870</literal>
      </binding>
    </result>
    <result>
      <binding name="refArea">
        <uri>http://worldbank.270a.info/classification/country/MV</uri>
      </binding>
      <binding name="obsValue">
        <literal datatype="http://www.w3.org/2001/XMLSchema#decimal">14401</literal>
      </binding>
    </result>
    <result>
      <binding name="refArea">
        <uri>http://worldbank.270a.info/classification/country/MH</uri>
      </binding>
      <binding name="obsValue">
        <literal datatype="http://www.w3.org/2001/XMLSchema#decimal">1104</literal>
      </binding>
    </result>
    <result>
      <binding name="refArea">
        <uri>http://worldbank.270a.info/classification/country/ML</uri>
      </binding>
      <binding name="obsValue">
        <literal datatype="http://www.w3.org/2001/XMLSchema#decimal">558593</literal>
      </binding>
    </result>
    <result>
      <binding name="refArea">
        <uri>http://worldbank.270a.info/classification/country/MT</uri>
      </binding>
      <binding name="obsValue">
        <literal datatype="http://www.w3.org/2001/XMLSchema#decimal">5475</literal>
      </binding>
    </result>
    <result>
      <binding name="refArea">
        <uri>http://worldbank.270a.info/classification/country/ME</uri>
      </binding>
      <binding name="obsValue">
        <literal datatype="http://www.w3.org/2001/XMLSchema#decimal">18010</literal>
      </binding>
    </result>
    <result>
      <binding name="refArea">
        <uri>http://worldbank.270a.info/classification/country/MN</uri>
      </binding>
      <binding name="obsValue">
        <literal datatype="http://www.w3.org/2001/XMLSchema#decimal">157413</literal>
      </binding>
    </result>
    <result>
      <binding name="refArea">
        <uri>http://worldbank.270a.info/classification/country/MZ</uri>
      </binding>
      <binding name="obsValue">
        <literal datatype="http://www.w3.org/2001/XMLSchema#decimal">524104</literal>
      </binding>
    </result>
    <result>
      <binding name="refArea">
        <uri>http://worldbank.270a.info/classification/country/MR</uri>
      </binding>
      <binding name="obsValue">
        <literal datatype="http://www.w3.org/2001/XMLSchema#decimal">151473</literal>
      </binding>
    </result>
    <result>
      <binding name="refArea">
        <uri>http://worldbank.270a.info/classification/country/MU</uri>
      </binding>
      <binding name="obsValue">
        <literal datatype="http://www.w3.org/2001/XMLSchema#decimal">39321</literal>
      </binding>
    </result>
    <result>
      <binding name="refArea">
        <uri>http://worldbank.270a.info/classification/country/MW</uri>
      </binding>
      <binding name="obsValue">
        <literal datatype="http://www.w3.org/2001/XMLSchema#decimal">702097</literal>
      </binding>
    </result>
    <result>
      <binding name="refArea">
        <uri>http://worldbank.270a.info/classification/country/MY</uri>
      </binding>
      <binding name="obsValue">
        <literal datatype="http://www.w3.org/2001/XMLSchema#decimal">562662</literal>
      </binding>
    </result>
    <result>
      <binding name="refArea">
        <uri>http://worldbank.270a.info/classification/country/NA</uri>
      </binding>
      <binding name="obsValue">
        <literal datatype="http://www.w3.org/2001/XMLSchema#decimal">103906</literal>
      </binding>
    </result>
    <result>
      <binding name="refArea">
        <uri>http://worldbank.270a.info/classification/country/NE</uri>
      </binding>
      <binding name="obsValue">
        <literal datatype="http://www.w3.org/2001/XMLSchema#decimal">559425</literal>
      </binding>
    </result>
    <result>
      <binding name="refArea">
        <uri>http://worldbank.270a.info/classification/country/NG</uri>
      </binding>
      <binding name="obsValue">
        <literal datatype="http://www.w3.org/2001/XMLSchema#decimal">6544206</literal>
      </binding>
    </result>
    <result>
      <binding name="refArea">
        <uri>http://worldbank.270a.info/classification/country/NO</uri>
      </binding>
      <binding name="obsValue">
        <literal datatype="http://www.w3.org/2001/XMLSchema#decimal">66235</literal>
      </binding>
    </result>
    <result>
      <binding name="refArea">
        <uri>http://worldbank.270a.info/classification/country/NZ</uri>
      </binding>
      <binding name="obsValue">
        <literal datatype="http://www.w3.org/2001/XMLSchema#decimal">62093</literal>
      </binding>
    </result>
    <result>
      <binding name="refArea">
        <uri>http://worldbank.270a.info/classification/country/OM</uri>
      </binding>
      <binding name="obsValue">
        <literal datatype="http://www.w3.org/2001/XMLSchema#decimal">144912</literal>
      </binding>
    </result>
    <result>
      <binding name="refArea">
        <uri>http://worldbank.270a.info/classification/country/PK</uri>
      </binding>
      <binding name="obsValue">
        <literal datatype="http://www.w3.org/2001/XMLSchema#decimal">12114518</literal>
      </binding>
    </result>
    <result>
      <binding name="refArea">
        <uri>http://worldbank.270a.info/classification/country/PA</uri>
      </binding>
      <binding name="obsValue">
        <literal datatype="http://www.w3.org/2001/XMLSchema#decimal">132986</literal>
      </binding>
    </result>
    <result>
      <binding name="refArea">
        <uri>http://worldbank.270a.info/classification/country/PH</uri>
      </binding>
      <binding name="obsValue">
        <literal datatype="http://www.w3.org/2001/XMLSchema#decimal">4025957</literal>
      </binding>
    </result>
    <result>
      <binding name="refArea">
        <uri>http://worldbank.270a.info/classification/country/PL</uri>
      </binding>
      <binding name="obsValue">
        <literal datatype="http://www.w3.org/2001/XMLSchema#decimal">1015282</literal>
      </binding>
    </result>
    <result>
      <binding name="refArea">
        <uri>http://worldbank.270a.info/classification/country/PR</uri>
      </binding>
      <binding name="obsValue">
        <literal datatype="http://www.w3.org/2001/XMLSchema#decimal">116383</literal>
      </binding>
    </result>
    <result>
      <binding name="refArea">
        <uri>http://worldbank.270a.info/classification/country/KP</uri>
      </binding>
      <binding name="obsValue">
        <literal datatype="http://www.w3.org/2001/XMLSchema#decimal">802435</literal>
      </binding>
    </result>
    <result>
      <binding name="refArea">
        <uri>http://worldbank.270a.info/classification/country/PT</uri>
      </binding>
      <binding name="obsValue">
        <literal datatype="http://www.w3.org/2001/XMLSchema#decimal">110420</literal>
      </binding>
    </result>
    <result>
      <binding name="refArea">
        <uri>http://worldbank.270a.info/classification/country/RO</uri>
      </binding>
      <binding name="obsValue">
        <literal datatype="http://www.w3.org/2001/XMLSchema#decimal">788028</literal>
      </binding>
    </result>
    <result>
      <binding name="refArea">
        <uri>http://worldbank.270a.info/classification/country/RU</uri>
      </binding>
      <binding name="obsValue">
        <literal datatype="http://www.w3.org/2001/XMLSchema#decimal">1619826</literal>
      </binding>
    </result>
    <result>
      <binding name="refArea">
        <uri>http://worldbank.270a.info/classification/country/SN</uri>
      </binding>
      <binding name="obsValue">
        <literal datatype="http://www.w3.org/2001/XMLSchema#decimal">541449</literal>
      </binding>
    </result>
    <result>
      <binding name="refArea">
        <uri>http://worldbank.270a.info/classification/country/SL</uri>
      </binding>
      <binding name="obsValue">
        <literal datatype="http://www.w3.org/2001/XMLSchema#decimal">236029</literal>
      </binding>
    </result>
    <result>
      <binding name="refArea">
        <uri>http://worldbank.270a.info/classification/country/SR</uri>
      </binding>
      <binding name="obsValue">
        <literal datatype="http://www.w3.org/2001/XMLSchema#decimal">35711</literal>
      </binding>
    </result>
    <result>
      <binding name="refArea">
        <uri>http://worldbank.270a.info/classification/country/SK</uri>
      </binding>
      <binding name="obsValue">
        <literal datatype="http://www.w3.org/2001/XMLSchema#decimal">73463</literal>
      </binding>
    </result>
    <result>
      <binding name="refArea">
        <uri>http://worldbank.270a.info/classification/country/SI</uri>
      </binding>
      <binding name="obsValue">
        <literal datatype="http://www.w3.org/2001/XMLSchema#decimal">20789</literal>
      </binding>
    </result>
    <result>
      <binding name="refArea">
        <uri>http://worldbank.270a.info/classification/country/SE</uri>
      </binding>
      <binding name="obsValue">
        <literal datatype="http://www.w3.org/2001/XMLSchema#decimal">136376</literal>
      </binding>
    </result>
    <result>
      <binding name="refArea">
        <uri>http://worldbank.270a.info/classification/country/SZ</uri>
      </binding>
      <binding name="obsValue">
        <literal datatype="http://www.w3.org/2001/XMLSchema#decimal">30313</literal>
      </binding>
    </result>
    <result>
      <binding name="refArea">
        <uri>http://worldbank.270a.info/classification/country/SC</uri>
      </binding>
      <binding name="obsValue">
        <literal datatype="http://www.w3.org/2001/XMLSchema#decimal">2809</literal>
      </binding>
    </result>
    <result>
      <binding name="refArea">
        <uri>http://worldbank.270a.info/classification/country/SY</uri>
      </binding>
      <binding name="obsValue">
        <literal datatype="http://www.w3.org/2001/XMLSchema#decimal">857823</literal>
      </binding>
    </result>
    <result>
      <binding name="refArea">
        <uri>http://worldbank.270a.info/classification/country/TG</uri>
      </binding>
      <binding name="obsValue">
        <literal datatype="http://www.w3.org/2001/XMLSchema#decimal">266715</literal>
      </binding>
    </result>
    <result>
      <binding name="refArea">
        <uri>http://worldbank.270a.info/classification/country/TH</uri>
      </binding>
      <binding name="obsValue">
        <literal datatype="http://www.w3.org/2001/XMLSchema#decimal">934970</literal>
      </binding>
    </result>
    <result>
      <binding name="refArea">
        <uri>http://worldbank.270a.info/classification/country/TJ</uri>
      </binding>
      <binding name="obsValue">
        <literal datatype="http://www.w3.org/2001/XMLSchema#decimal">518096</literal>
      </binding>
    </result>
    <result>
      <binding name="refArea">
        <uri>http://worldbank.270a.info/classification/country/TM</uri>
      </binding>
      <binding name="obsValue">
        <literal datatype="http://www.w3.org/2001/XMLSchema#decimal">205437</literal>
      </binding>
    </result>
    <result>
      <binding name="refArea">
        <uri>http://worldbank.270a.info/classification/country/TO</uri>
      </binding>
      <binding name="obsValue">
        <literal datatype="http://www.w3.org/2001/XMLSchema#decimal">2238</literal>
      </binding>
    </result>
    <result>
      <binding name="refArea">
        <uri>http://worldbank.270a.info/classification/country/TT</uri>
      </binding>
      <binding name="obsValue">
        <literal datatype="http://www.w3.org/2001/XMLSchema#decimal">36581</literal>
      </binding>
    </result>
    <result>
      <binding name="refArea">
        <uri>http://worldbank.270a.info/classification/country/TV</uri>
      </binding>
      <binding name="obsValue">
        <literal datatype="http://www.w3.org/2001/XMLSchema#decimal">228</literal>
      </binding>
    </result>
    <result>
      <binding name="refArea">
        <uri>http://worldbank.270a.info/classification/country/UG</uri>
      </binding>
      <binding name="obsValue">
        <literal datatype="http://www.w3.org/2001/XMLSchema#decimal">1516785</literal>
      </binding>
    </result>
    <result>
      <binding name="refArea">
        <uri>http://worldbank.270a.info/classification/country/UA</uri>
      </binding>
      <binding name="obsValue">
        <literal datatype="http://www.w3.org/2001/XMLSchema#decimal">489747</literal>
      </binding>
    </result>
    <result>
      <binding name="refArea">
        <uri>http://worldbank.270a.info/classification/country/US</uri>
      </binding>
      <binding name="obsValue">
        <literal datatype="http://www.w3.org/2001/XMLSchema#decimal">4464611</literal>
      </binding>
    </result>
    <result>
      <binding name="refArea">
        <uri>http://worldbank.270a.info/classification/country/UZ</uri>
      </binding>
      <binding name="obsValue">
        <literal datatype="http://www.w3.org/2001/XMLSchema#decimal">1870236</literal>
      </binding>
    </result>
    <result>
      <binding name="refArea">
        <uri>http://worldbank.270a.info/classification/country/VC</uri>
      </binding>
      <binding name="obsValue">
        <literal datatype="http://www.w3.org/2001/XMLSchema#decimal">4090</literal>
      </binding>
    </result>
    <result>
      <binding name="refArea">
        <uri>http://worldbank.270a.info/classification/country/VU</uri>
      </binding>
      <binding name="obsValue">
        <literal datatype="http://www.w3.org/2001/XMLSchema#decimal">4459</literal>
      </binding>
    </result>
    <result>
      <binding name="refArea">
        <uri>http://worldbank.270a.info/classification/country/PS</uri>
      </binding>
      <binding name="obsValue">
        <literal datatype="http://www.w3.org/2001/XMLSchema#decimal">101970</literal>
      </binding>
    </result>
    <result>
      <binding name="refArea">
        <uri>http://worldbank.270a.info/classification/country/WS</uri>
      </binding>
      <binding name="obsValue">
        <literal datatype="http://www.w3.org/2001/XMLSchema#decimal">3895</literal>
      </binding>
    </result>
    <result>
      <binding name="refArea">
        <uri>http://worldbank.270a.info/classification/country/ZA</uri>
      </binding>
      <binding name="obsValue">
        <literal datatype="http://www.w3.org/2001/XMLSchema#decimal">1968283</literal>
      </binding>
    </result>
    <result>
      <binding name="refArea">
        <uri>http://worldbank.270a.info/classification/country/ZM</uri>
      </binding>
      <binding name="obsValue">
        <literal datatype="http://www.w3.org/2001/XMLSchema#decimal">287072</literal>
      </binding>
    </result>
    <result>
      <binding name="refArea">
        <uri>http://worldbank.270a.info/classification/country/ZW</uri>
      </binding>
      <binding name="obsValue">
        <literal datatype="http://www.w3.org/2001/XMLSchema#decimal">661981</literal>
      </binding>
    </result>
  </results>
</sparql>
